{
  "timestamp": "2026-07-08T20:01:42.682Z",
  "war_day": 130,
  "probabilities": {
    "1개월 내 (~3월)": 24.6,
    "2~3개월 (4~5월)": 42.4,
    "4~6개월 (6~8월)": 22.5,
    "7~12개월 (9월~27/2월)": 8.5,
    "1년 초과": 2
  },
  "factors": [
    {
      "factor": "트럼프 대통령 4-5주 예상 발언",
      "impact": "2~3개월 내 종전 확률 상승",
      "weight": "+8%p (2~3개월) (잔존30%)",
      "direction": "shorten",
      "detail": "트럼프 대통령이 공개적으로 전쟁이 \"4-5주 내\"에 끝날 것이라고 발언했습니다.",
      "keywords": [
        "trump",
        "4 week",
        "5 week",
        "timeline",
        "end war"
      ],
      "applied": "2026-03-01",
      "active": true,
      "decay": 0.3
    },
    {
      "factor": "이스라엘 제공권 장악 (이란 방공 80% 파괴)",
      "impact": "단기 종전 가능성 증가",
      "weight": "+4%p (1개월내), +6%p (2~3개월) (잔존40%)",
      "direction": "shorten",
      "detail": "이스라엘이 이란 방공망의 핵심을 무력화했습니다.",
      "keywords": [
        "air superi",
        "air defens",
        "s-300",
        "s-400",
        "radar",
        "anti-air"
      ],
      "applied": "2026-03-01",
      "active": true,
      "decay": 0.4
    },
    {
      "factor": "이란 미사일 능력 급감 (휴전10:확전4)",
      "impact": "전쟁 지속 능력 약화로 단기 종전 가능성 증가",
      "weight": "+0.0%p (1개월내), +0.0%p (2~3개월) (잔존40%)",
      "direction": "shorten",
      "detail": "이란의 보복 미사일 타격 능력이 약 90% 감소했습니다.",
      "keywords": [
        "missile",
        "ballistic",
        "launch",
        "strike capab"
      ],
      "applied": "2026-03-02",
      "active": true,
      "decay": 0.4
    },
    {
      "factor": "호르무즈 해협 봉쇄 → 국제 경제 압력",
      "impact": "경제적 압력으로 빠른 해결 촉구",
      "weight": "+3%p (1개월내), +5%p (2~3개월) (잔존40%)",
      "direction": "shorten",
      "detail": "세계 원유의 약 20%가 호르무즈 해협을 통과합니다.",
      "keywords": [
        "hormuz",
        "strait",
        "oil price",
        "blockade",
        "shipping",
        "tanker"
      ],
      "applied": "2026-03-01",
      "active": true,
      "decay": 0.4
    },
    {
      "factor": "9개국 참전 - 분쟁 복잡성 증가",
      "impact": "다자간 분쟁으로 협상 복잡화",
      "weight": "+5%p (4~6개월), +3%p (7~12개월) (잔존30%)",
      "direction": "lengthen",
      "detail": "참전국이 많을수록 휴전 협상이 복잡해집니다.",
      "keywords": [
        "coalition",
        "allies",
        "nato",
        "joint operation",
        "multinational"
      ],
      "applied": "2026-03-02",
      "active": true,
      "decay": 0.3
    },
    {
      "factor": "하메네이 사망 - 이란 지도부 공백",
      "impact": "정권 붕괴 가능성과 내부 혼란 장기화 위험",
      "weight": "+4%p (2~3개월), +4%p (4~6개월) (잔존30%)",
      "direction": "mixed",
      "detail": "최고지도자의 사망으로 정권 내부에 큰 혼란이 발생합니다.",
      "keywords": [
        "khamenei",
        "supreme leader",
        "succession",
        "leadership",
        "regime"
      ],
      "applied": "2026-03-03",
      "active": true,
      "decay": 0.3
    },
    {
      "factor": "쿠르드족 지상군 이란 국경 진입",
      "impact": "지상전 확대로 전쟁 장기화 위험",
      "weight": "+4%p (4~6개월), +3%p (7~12개월) (잔존30%)",
      "direction": "lengthen",
      "detail": "쿠르드 페쉬메르가 부대가 북부 전선을 열었습니다.",
      "keywords": [
        "kurd",
        "peshmerga",
        "ground",
        "border",
        "northern front"
      ],
      "applied": "2026-03-04",
      "active": true,
      "decay": 0.3
    },
    {
      "factor": "이란 3/5 CIA 통한 협상 시도",
      "impact": "이란의 협상 의지 → 단기 종전 가능성 증가",
      "weight": "+5%p (1개월내), +8%p (2~3개월) (잔존30%)",
      "direction": "shorten",
      "detail": "이란이 비밀 채널을 통해 협상을 시도했습니다.",
      "keywords": [
        "cia",
        "backchannel",
        "secret talk",
        "negotiat",
        "iran offer",
        "surrender"
      ],
      "applied": "2026-03-05",
      "active": true,
      "decay": 0.3
    },
    {
      "factor": "걸프전(42일) 패턴 유사성",
      "impact": "제공권→지상작전→빠른 종결 패턴",
      "weight": "참고: 걸프전 42일, 코소보 78일, 포클랜드 74일",
      "direction": "reference",
      "detail": "이번 전쟁은 걸프전과 매우 유사한 패턴을 보입니다.",
      "keywords": [
        "gulf war",
        "desert storm",
        "pattern",
        "historical"
      ],
      "applied": "2026-02-28",
      "active": true,
      "decay": 1
    },
    {
      "factor": "협상/외교 뉴스 6건 감지",
      "impact": "외교적 해결 움직임 포착",
      "weight": "+0.01%p (1개월내), +0.01%p (2~3개월)",
      "direction": "shorten",
      "detail": "실시간 뉴스에서 협상 관련 기사 6건이 감지되었습니다.",
      "keywords": [
        "negotiat",
        "talks",
        "dialog",
        "diplomat",
        "mediati"
      ],
      "applied": "실시간",
      "active": true,
      "decay": 1
    },
    {
      "factor": "지역 확산 뉴스 18건 감지",
      "impact": "주변국 대규모 연루 → 장기화 위험 높음",
      "weight": "+0.02%p (4~6개월), +0.02%p (7~12개월)",
      "direction": "lengthen",
      "detail": "주변국을 언급하는 기사 18건이 감지되었습니다.",
      "keywords": [
        "saudi",
        "uae",
        "qatar",
        "iraq",
        "lebanon",
        "turkey"
      ],
      "applied": "실시간",
      "active": true,
      "decay": 1
    },
    {
      "factor": "미 상원 전쟁 결의안 부결",
      "impact": "미국 내 정치적 지지로 군사작전 지속 가능",
      "weight": "+3%p (2~3개월), +2%p (4~6개월) (잔존30%)",
      "direction": "mixed",
      "detail": "미 상원이 전쟁권한 제한 결의안을 부결시켰습니다.",
      "keywords": [
        "senate",
        "resolution",
        "war powers",
        "congress",
        "vote"
      ],
      "applied": "2026-03-04",
      "active": true,
      "decay": 0.3
    },
    {
      "factor": "사우디/UAE 연합군 참전",
      "impact": "이란 포위망 강화 → 조기 항복 가능성",
      "weight": "+3%p (1개월내), +5%p (2~3개월) (잔존30%)",
      "direction": "shorten",
      "detail": "사우디와 UAE가 연합군에 합류했습니다.",
      "keywords": [
        "saudi",
        "uae",
        "coalition",
        "join",
        "alliance",
        "gcc"
      ],
      "applied": "2026-03-03",
      "active": true,
      "decay": 0.3
    },
    {
      "factor": "[중대 이벤트] 교전국 정권 붕괴/쿠데타",
      "impact": "교전국 정권 붕괴 또는 쿠데타. 이라크(2003): 바그다드 함락 후 3주 내 주요 전투 종료. 리비아(2011): 트리폴리 함락 후 2개월 내 종전.",
      "weight": "+6.7%p (1개월내), +5.3%p (2~3개월), +1.3%p (4~6개월), -3.3%p (7~12개월), -2.7%p (1년초과)",
      "direction": "shorten",
      "detail": "교전국 정권 붕괴 또는 쿠데타. 이라크(2003): 바그다드 함락 후 3주 내 주요 전투 종료. 리비아(2011): 트리폴리 함락 후 2개월 내 종전.\n\n신뢰도: 높음 (67%), 관련 기사 2건 감지.\n관련: Tehran teemed with Khamenei mourners, but divisions – and demands for change – remain",
      "keywords": [
        "regime",
        "collaps",
        "regime",
        "fall",
        "government",
        "fall",
        "capital",
        "fall",
        "capital",
        "captur",
        "coup",
        "detat",
        "government",
        "overthrow",
        "regime",
        "change"
      ],
      "applied": "2026-07-08",
      "active": true,
      "severity": "critical"
    },
    {
      "factor": "[중대 이벤트] 일방적 전투 축소/자제 선언",
      "impact": "교전국의 일방적 전투 축소 또는 자제 선언. 역사적으로 패전국의 자발적 전선 축소는 80% 이상 공식 항복의 전조.",
      "weight": "+3.3%p (1개월내), +4.7%p (2~3개월), -2.0%p (4~6개월), -2.0%p (7~12개월), -0.7%p (1년초과)",
      "direction": "shorten",
      "detail": "교전국의 일방적 전투 축소 또는 자제 선언. 역사적으로 패전국의 자발적 전선 축소는 80% 이상 공식 항복의 전조.\n\n신뢰도: 높음 (67%), 관련 기사 2건 감지.\n관련: Iran Truce ‘Over,’ Trump Says, as He Threatens More Strikes",
      "keywords": [
        "halt",
        "attack",
        "stop",
        "attack",
        "neighb",
        "no more",
        "attack",
        "withdraw",
        "forces",
        "pull back",
        "troops",
        "unilateral",
        "ceasefire",
        "reduce",
        "operation",
        "de-escalat",
        "announc",
        "restrain",
        "attack",
        "not attack",
        "suspend",
        "operation"
      ],
      "applied": "2026-07-08",
      "active": true,
      "severity": "high"
    },
    {
      "factor": "[중대 이벤트] 수도 직접 공격/포위",
      "impact": "수도 직접 공격. 베오그라드(1999): 78일 폭격 후 항복. 바그다드(2003): 21일만에 함락. 수도 타격은 전쟁 지속 의지를 급격히 약화.",
      "weight": "+2.7%p (1개월내), +4.0%p (2~3개월), -1.3%p (4~6개월), -1.3%p (7~12개월), -0.7%p (1년초과)",
      "direction": "shorten",
      "detail": "수도 직접 공격. 베오그라드(1999): 78일 폭격 후 항복. 바그다드(2003): 21일만에 함락. 수도 타격은 전쟁 지속 의지를 급격히 약화.\n\n신뢰도: 높음 (67%), 관련 기사 2건 감지.\n관련: US launches ​strikes against Iran after attacks on vessels in strait ​of ​Hormuz",
      "keywords": [
        "capital",
        "bomb",
        "capital",
        "strike",
        "capital",
        "attack",
        "capital",
        "siege",
        "capital",
        "pound",
        "capital",
        "explosion",
        "tehran",
        "bomb",
        "tehran",
        "strike",
        "tehran",
        "pound",
        "tehran",
        "explosion"
      ],
      "applied": "2026-07-08",
      "active": true,
      "severity": "high"
    },
    {
      "factor": "금값 사상최고 ($4090.3/oz)",
      "impact": "안전자산 수요 폭증 → 글로벌 불안 심화",
      "weight": "+2%p (4-6개월)",
      "direction": "lengthen",
      "detail": "금 가격이 온스당 $4090.3로 사상 최고 수준입니다. 투자자들이 안전자산으로 대거 이동하고 있으며, 이는 전쟁 장기화에 대한 시장의 우려를 반영합니다.",
      "keywords": [
        "gold",
        "safe haven",
        "precious metal",
        "investor"
      ],
      "applied": "실시간",
      "active": true
    },
    {
      "factor": "미국 10년 국채금리 4.57% (고금리 지속)",
      "impact": "전쟁 자금 조달 비용 증가",
      "weight": "+1%p (4-6개월)",
      "direction": "mixed",
      "detail": "미국 10년물 국채금리가 4.57%로 높은 수준을 유지하고 있습니다. 전쟁 자금 조달 비용이 증가하며, 장기전의 경제적 부담이 커지고 있습니다.",
      "keywords": [
        "treasury",
        "yield",
        "bond",
        "interest rate",
        "fed"
      ],
      "applied": "실시간",
      "active": true
    }
  ],
  "news_signals": {
    "ceasefire_mentions": 10,
    "escalation_mentions": 4,
    "negotiation_mentions": 6,
    "casualty_mentions": 2,
    "peace_mentions": 2,
    "regional_spread": 18,
    "total_articles": 50,
    "new_articles": 50,
    "unique_events": 48,
    "duplicates_removed": 2
  },
  "latest_news": [
    {
      "title": "Gaza’s World Cup screenings – in pictures",
      "link": "https://www.theguardian.com/world/gallery/2026/jul/08/gazas-world-cup-screenings-in-pictures",
      "pubDate": "Wed, 08 Jul 2026 20:00:21 GMT",
      "source": "guardian",
      "snippet": "Mohamed al-Wahidi died when a missile struck his taxi shortly before Egypt played Argentina in their last 16 World Cup match. He had organised the screening of World Cup games across the Gaza Strip, w",
      "isNew": true,
      "_sourceCount": 1,
      "_isDuplicated": true,
      "_clusterSize": 2,
      "_isDuplicate": false
    },
    {
      "title": "In Israel, Rahm Emanuel Calls for End of Unconditional U.S. Support",
      "link": "https://www.nytimes.com/2026/07/07/us/politics/rahm-emanuel-speech-israel.html",
      "pubDate": "Wed, 08 Jul 2026 19:55:33 +0000",
      "source": "nytimes",
      "snippet": "The former Chicago mayor, a Democrat exploring a 2028 presidential run, delivered a speech in Tel Aviv that was sharply critical of Benjamin Netanyahu.",
      "isNew": true,
      "_sourceCount": 1,
      "_isDuplicated": false,
      "_clusterSize": 1,
      "_isDuplicate": false
    },
    {
      "title": "Iran Truce ‘Over,’ Trump Says, as He Threatens More Strikes",
      "link": "https://www.nytimes.com/2026/07/08/world/middleeast/iran-truce-trump.html",
      "pubDate": "Wed, 08 Jul 2026 19:52:04 +0000",
      "source": "nytimes",
      "snippet": "A wave of U.S. attacks were followed by Iranian strikes, halting ship traffic in the Strait of Hormuz again. Oil prices rose sharply.",
      "isNew": true,
      "_sourceCount": 1,
      "_isDuplicated": false,
      "_clusterSize": 1,
      "_isDuplicate": false
    },
    {
      "title": "Iraqis Turn Out in Droves to Mourn Khamenei and Show Solidarity",
      "link": "https://www.nytimes.com/2026/07/08/world/middleeast/iraq-funeral-ayatollah-khamenei.html",
      "pubDate": "Wed, 08 Jul 2026 19:47:16 +0000",
      "source": "nytimes",
      "snippet": "In Najaf and Karbala, home to two of Shiite Islam’s holiest sites, hundreds of thousands joined commemorations for Ayatollah Ali Khamenei, who extended Iran’s influence in Iraq.",
      "isNew": true,
      "_sourceCount": 1,
      "_isDuplicated": false,
      "_clusterSize": 1,
      "_isDuplicate": false
    },
    {
      "title": "The Symbols We Saw at Khamenei’s Funeral",
      "link": "https://www.nytimes.com/video/world/middleeast/100000011012446/the-symbols-we-saw-at-khameneis-funeral.html",
      "pubDate": "Wed, 08 Jul 2026 19:41:39 +0000",
      "source": "nytimes",
      "snippet": "Abdi Latif Dahir, a Middle East correspondent for The Times, explains the messages behind recurring symbols at the dayslong funeral for Ayatollah Ali Khamenei.",
      "isNew": true,
      "_sourceCount": 1,
      "_isDuplicated": false,
      "_clusterSize": 1,
      "_isDuplicate": false
    },
    {
      "title": "As U.S.-Iran Cease-Fire Frays, Trump Faces a Muddled War and Unpalatable Options",
      "link": "https://www.nytimes.com/2026/07/08/us/politics/trump-iran-war.html",
      "pubDate": "Wed, 08 Jul 2026 19:31:18 +0000",
      "source": "nytimes",
      "snippet": "The president appears to be confronting the consequences of a cease-fire deal cobbled together in haste, with little movement toward resolving the key issues driving the conflict.",
      "isNew": true,
      "_sourceCount": 1,
      "_isDuplicated": false,
      "_clusterSize": 1,
      "_isDuplicate": false
    },
    {
      "title": "Five key takeaways from the NATO summit in Ankara",
      "link": "https://www.aljazeera.com/news/2026/7/8/five-key-takeaways-from-the-nato-summit-in-ankara?traffic_source=rss",
      "pubDate": "Wed, 08 Jul 2026 19:06:35 +0000",
      "source": "aljazeera",
      "snippet": "Trump dominates summit with anti-Europe and Iran diatribes as NATO pledges to expand defence budgets and Ukraine support",
      "isNew": true,
      "_sourceCount": 1,
      "_isDuplicated": false,
      "_clusterSize": 1,
      "_isDuplicate": false
    },
    {
      "title": "Atmosphere in Iran remains highly charged after Ayatollah’s funeral and escalation of grievances with US",
      "link": "https://www.theguardian.com/world/2026/jul/08/atmosphere-in-iran-remains-highly-charged-after-ayatollahs-funeral-and-escalation-of-grievances-with-us",
      "pubDate": "Wed, 08 Jul 2026 19:05:46 GMT",
      "source": "guardian",
      "snippet": "World is witnessing a turning point, says ministry spokesperson, as Iran seeks to assert independence amid rising tensionsBefore a foreign ministry press briefing at the Grand Hotel Tehran, the assemb",
      "isNew": true,
      "_sourceCount": 1,
      "_isDuplicated": false,
      "_clusterSize": 1,
      "_isDuplicate": false
    },
    {
      "title": "Sabre-rattling to ‘tremendous love’: erratic Trump dominates final hours of Nato summit",
      "link": "https://www.theguardian.com/world/2026/jul/08/erratic-trump-dominates-final-hours-nato-summit",
      "pubDate": "Wed, 08 Jul 2026 19:00:12 GMT",
      "source": "guardian",
      "snippet": "Alliance leaders, who had feared the worst, will hail US president’s renewed support for article 5 as key victoryAn erratic and at times irascible Donald Trump has said he felt a “tremendous love” fro",
      "isNew": true,
      "_sourceCount": 1,
      "_isDuplicated": false,
      "_clusterSize": 1,
      "_isDuplicate": false
    },
    {
      "title": "Trump says US ‘may take over Kharg Island’: Here’s what you need to know",
      "link": "https://www.aljazeera.com/news/2026/7/8/trump-says-us-may-take-over-kharg-island-heres-what-you-need-to-know?traffic_source=rss",
      "pubDate": "Wed, 08 Jul 2026 18:52:13 +0000",
      "source": "aljazeera",
      "snippet": "Kharg Island, pivotal to Iran&#039;s oil exports, becomes focal point as Trump renews threats amid rising Gulf tensions.",
      "isNew": true,
      "_sourceCount": 1,
      "_isDuplicated": false,
      "_clusterSize": 1,
      "_isDuplicate": false
    },
    {
      "title": "War on Gaza draws large crowds to Khamenei’s funeral in Iraq",
      "link": "https://www.aljazeera.com/video/newsfeed/2026/7/8/war-on-gaza-draws-large-crowds-to-khameneis-funeral-in-iraq?traffic_source=rss",
      "pubDate": "Wed, 08 Jul 2026 18:51:32 +0000",
      "source": "aljazeera",
      "snippet": "More than a million mourners packed streets in Najaf, Iraq for Iranian Supreme Leader Ali Khamenei’s funeral procession.",
      "isNew": true,
      "_sourceCount": 1,
      "_isDuplicated": false,
      "_clusterSize": 1,
      "_isDuplicate": false
    },
    {
      "title": "Oil Market Calm Shattered by Fresh Hostilities Between US and Iran",
      "link": "https://www.nytimes.com/2026/07/08/business/energy-environment/iran-war-oil-prices.html",
      "pubDate": "Wed, 08 Jul 2026 18:45:17 +0000",
      "source": "nytimes",
      "snippet": "Oil prices are likely to remain volatile as long as the United States and Iran are unable to resolve the status of the Strait of Hormuz.",
      "isNew": true,
      "_sourceCount": 1,
      "_isDuplicated": false,
      "_clusterSize": 1,
      "_isDuplicate": false
    },
    {
      "title": "Israeli air strikes in Gaza kill eight, including two children",
      "link": "https://www.aljazeera.com/news/2026/7/8/israeli-air-strikes-in-gaza-kill-eight-including-two-children?traffic_source=rss",
      "pubDate": "Wed, 08 Jul 2026 18:35:11 +0000",
      "source": "aljazeera",
      "snippet": "Medics report 12 injuries alongside eight deaths in Gaza as Israeli air strikes target civilians and displaced families.",
      "isNew": true,
      "_sourceCount": 1,
      "_isDuplicated": false,
      "_clusterSize": 1,
      "_isDuplicate": false
    },
    {
      "title": "Trump says he ‘may be gone’ as he declares himself Iran’s No. 1 target",
      "link": "https://www.aljazeera.com/video/newsfeed/2026/7/8/trump-says-he-may-be-gone-as-he-declares-himself-irans-no-1-target?traffic_source=rss",
      "pubDate": "Wed, 08 Jul 2026 18:33:08 +0000",
      "source": "aljazeera",
      "snippet": "US President Donald Trump declared himself Iran’s ‘No. 1 target’ after claiming their leaders have been eliminated ",
      "isNew": true,
      "_sourceCount": 1,
      "_isDuplicated": false,
      "_clusterSize": 1,
      "_isDuplicate": false
    },
    {
      "title": "US and Iran threaten return to war after fiercest exchange of fire since truce",
      "link": "https://www.theguardian.com/world/2026/jul/08/iran-us-war-ceasefire-peace-agreement-strikes-strait-of-hormuz",
      "pubDate": "Wed, 08 Jul 2026 18:32:47 GMT",
      "source": "guardian",
      "snippet": "Ceasefire appears close to collapse as two militaries target each other after after Iran strikes three commercial vesselsIran and the US have threatened to reignite their conflict after the most exten",
      "isNew": true,
      "_sourceCount": 1,
      "_isDuplicated": false,
      "_clusterSize": 1,
      "_isDuplicate": false
    }
  ],
  "news_digest": {
    "categories": [
      {
        "category_id": "politics",
        "category_name": "국내 정치",
        "category_icon": "🏛️",
        "count": 18,
        "new_count": 18,
        "articles": [
          {
            "title": "In Israel, Rahm Emanuel Calls for End of Unconditional U.S. Support",
            "link": "https://www.nytimes.com/2026/07/07/us/politics/rahm-emanuel-speech-israel.html",
            "source": "nytimes",
            "sources": [
              "nytimes"
            ],
            "pubDate": "Wed, 08 Jul 2026 19:55:33 +0000",
            "snippet": "The former Chicago mayor, a Democrat exploring a 2028 presidential run, delivered a speech in Tel Aviv that was sharply critical of Benjamin Netanyahu.",
            "isNew": true
          },
          {
            "title": "Iraqis Turn Out in Droves to Mourn Khamenei and Show Solidarity",
            "link": "https://www.nytimes.com/2026/07/08/world/middleeast/iraq-funeral-ayatollah-khamenei.html",
            "source": "nytimes",
            "sources": [
              "nytimes"
            ],
            "pubDate": "Wed, 08 Jul 2026 19:47:16 +0000",
            "snippet": "In Najaf and Karbala, home to two of Shiite Islam’s holiest sites, hundreds of thousands joined commemorations for Ayatollah Ali Khamenei, who extended Iran’s influence in Iraq.",
            "isNew": true
          },
          {
            "title": "The Symbols We Saw at Khamenei’s Funeral",
            "link": "https://www.nytimes.com/video/world/middleeast/100000011012446/the-symbols-we-saw-at-khameneis-funeral.html",
            "source": "nytimes",
            "sources": [
              "nytimes"
            ],
            "pubDate": "Wed, 08 Jul 2026 19:41:39 +0000",
            "snippet": "Abdi Latif Dahir, a Middle East correspondent for The Times, explains the messages behind recurring symbols at the dayslong funeral for Ayatollah Ali Khamenei.",
            "isNew": true
          },
          {
            "title": "As U.S.-Iran Cease-Fire Frays, Trump Faces a Muddled War and Unpalatable Options",
            "link": "https://www.nytimes.com/2026/07/08/us/politics/trump-iran-war.html",
            "source": "nytimes",
            "sources": [
              "nytimes"
            ],
            "pubDate": "Wed, 08 Jul 2026 19:31:18 +0000",
            "snippet": "The president appears to be confronting the consequences of a cease-fire deal cobbled together in haste, with little movement toward resolving the key issues driving the conflict.",
            "isNew": true
          },
          {
            "title": "Sabre-rattling to ‘tremendous love’: erratic Trump dominates final hours of Nato summit",
            "link": "https://www.theguardian.com/world/2026/jul/08/erratic-trump-dominates-final-hours-nato-summit",
            "source": "guardian",
            "sources": [
              "guardian"
            ],
            "pubDate": "Wed, 08 Jul 2026 19:00:12 GMT",
            "snippet": "Alliance leaders, who had feared the worst, will hail US president’s renewed support for article 5 as key victoryAn erratic and at times irascible Donald Trump has said he felt a “tremendous love” fro",
            "isNew": true
          },
          {
            "title": "War on Gaza draws large crowds to Khamenei’s funeral in Iraq",
            "link": "https://www.aljazeera.com/video/newsfeed/2026/7/8/war-on-gaza-draws-large-crowds-to-khameneis-funeral-in-iraq?traffic_source=rss",
            "source": "aljazeera",
            "sources": [
              "aljazeera"
            ],
            "pubDate": "Wed, 08 Jul 2026 18:51:32 +0000",
            "snippet": "More than a million mourners packed streets in Najaf, Iraq for Iranian Supreme Leader Ali Khamenei’s funeral procession.",
            "isNew": true
          },
          {
            "title": "Trump says he ‘may be gone’ as he declares himself Iran’s No. 1 target",
            "link": "https://www.aljazeera.com/video/newsfeed/2026/7/8/trump-says-he-may-be-gone-as-he-declares-himself-irans-no-1-target?traffic_source=rss",
            "source": "aljazeera",
            "sources": [
              "aljazeera"
            ],
            "pubDate": "Wed, 08 Jul 2026 18:33:08 +0000",
            "snippet": "US President Donald Trump declared himself Iran’s ‘No. 1 target’ after claiming their leaders have been eliminated ",
            "isNew": true
          },
          {
            "title": "Khamenei's coffin carried through Shia shrines as ceremonies held in Iraq",
            "link": "https://www.bbc.co.uk/news/articles/cp9le3kjj8eo?at_medium=RSS&at_campaign=rss",
            "source": "bbc",
            "sources": [
              "bbc"
            ],
            "pubDate": "Wed, 08 Jul 2026 14:56:24 GMT",
            "snippet": "The remains of Iran's late supreme leader are transported to Najaf and Karbala, as funeral ceremonies continue for a fifth day.",
            "isNew": true
          },
          {
            "title": "Trump on Iran: ‘We’ll probably hit them hard again tonight’",
            "link": "https://www.aljazeera.com/video/newsfeed/2026/7/8/trump-on-iran-well-probably-hit-them-hard-again?traffic_source=rss",
            "source": "aljazeera",
            "sources": [
              "aljazeera"
            ],
            "pubDate": "Wed, 08 Jul 2026 14:20:03 +0000",
            "snippet": "US President Donald Trump says the US will ‘probably’ carry out another round of strikes on Iran on Wednesday night.",
            "isNew": true
          },
          {
            "title": "‘Down with the USA’: US influencer Jackson Hinkle attends Khamenei’s funera",
            "link": "https://www.aljazeera.com/video/newsfeed/2026/7/8/down-with-the-usa-us-influencer-jackson-hinkle-attends-khameneis-funera?traffic_source=rss",
            "source": "aljazeera",
            "sources": [
              "aljazeera"
            ],
            "pubDate": "Wed, 08 Jul 2026 14:17:23 +0000",
            "snippet": "‘Down with the USA’: US influencer Jackson Hinkle attends Khamenei’s funeral",
            "isNew": true
          }
        ]
      },
      {
        "category_id": "military",
        "category_name": "군사 작전",
        "category_icon": "⚔️",
        "count": 10,
        "new_count": 10,
        "articles": [
          {
            "title": "Gaza’s World Cup screenings – in pictures",
            "link": "https://www.theguardian.com/world/gallery/2026/jul/08/gazas-world-cup-screenings-in-pictures",
            "source": "guardian",
            "sources": [
              "guardian"
            ],
            "pubDate": "Wed, 08 Jul 2026 20:00:21 GMT",
            "snippet": "Mohamed al-Wahidi died when a missile struck his taxi shortly before Egypt played Argentina in their last 16 World Cup match. He had organised the screening of World Cup games across the Gaza Strip, w",
            "isNew": true
          },
          {
            "title": "Iran Truce ‘Over,’ Trump Says, as He Threatens More Strikes",
            "link": "https://www.nytimes.com/2026/07/08/world/middleeast/iran-truce-trump.html",
            "source": "nytimes",
            "sources": [
              "nytimes"
            ],
            "pubDate": "Wed, 08 Jul 2026 19:52:04 +0000",
            "snippet": "A wave of U.S. attacks were followed by Iranian strikes, halting ship traffic in the Strait of Hormuz again. Oil prices rose sharply.",
            "isNew": true
          },
          {
            "title": "NATO pledges 70 billion euros for Ukraine as Trump praises peace ‘progress’",
            "link": "https://www.aljazeera.com/news/2026/7/8/nato-pledges-70-billion-euros-for-ukraine-as-trump-praises-peace-progress?traffic_source=rss",
            "source": "aljazeera",
            "sources": [
              "aljazeera"
            ],
            "pubDate": "Wed, 08 Jul 2026 17:24:45 +0000",
            "snippet": "Trump says US will &#039;show&#039; Ukraine how to produce Patriot missile systems during a friendly appearance with Zelenskyy.",
            "isNew": true
          },
          {
            "title": "Pakistan military says 42 killed in fighter attacks in Balochistan",
            "link": "https://www.aljazeera.com/news/2026/7/8/pakistan-military-says-42-killed-in-fighter-attacks-in-balochistan?traffic_source=rss",
            "source": "aljazeera",
            "sources": [
              "aljazeera"
            ],
            "pubDate": "Wed, 08 Jul 2026 16:07:45 +0000",
            "snippet": "Military spokesman warns fighters &#039;we will chase you, we will hurt you&#039; amid the spate of deadly ambushes.",
            "isNew": true
          },
          {
            "title": "Zelenskyy seeks NATO support as Russia continues attacks",
            "link": "https://www.aljazeera.com/video/newsfeed/2026/7/8/zelenskyy-seeks-nato-support-as-russia-continues-attacks?traffic_source=rss",
            "source": "aljazeera",
            "sources": [
              "aljazeera"
            ],
            "pubDate": "Wed, 08 Jul 2026 15:18:30 +0000",
            "snippet": "At the NATO summit, Ukrainian President Volodymyr Zelenskyy had urged European allies to build missiles.",
            "isNew": true
          },
          {
            "title": "U.S. Strikes Iran and Reimposes Sanctions After Tanker Attacks",
            "link": "https://www.nytimes.com/2026/07/07/us/politics/us-strikes-iran-tanker-attacks.html",
            "source": "nytimes",
            "sources": [
              "nytimes"
            ],
            "pubDate": "Wed, 08 Jul 2026 13:18:48 +0000",
            "snippet": "The military operation came hours after the U.S. Treasury revoked a waiver allowing global sales of Iranian oil.",
            "isNew": true
          },
          {
            "title": "US and Iran trade strikes after tankers hit in Strait of Hormuz",
            "link": "https://www.bbc.co.uk/news/articles/cwykq59jwpvo?at_medium=RSS&at_campaign=rss",
            "source": "bbc",
            "sources": [
              "bbc"
            ],
            "pubDate": "Wed, 08 Jul 2026 08:11:50 GMT",
            "snippet": "The US military says it hit missile sites and command centres while Iran says it attacked US bases.",
            "isNew": true
          },
          {
            "title": "Palestinians brace as Israeli settler figures in coalition seek to cement West Bank gains before election",
            "link": "https://www.theguardian.com/world/2026/jul/08/palestinians-brace-as-israeli-settler-figures-in-coalition-seek-to-cement-west-bank-gains-before-election",
            "source": "guardian",
            "sources": [
              "guardian"
            ],
            "pubDate": "Wed, 08 Jul 2026 04:00:20 GMT",
            "snippet": "Growing number of farm outposts using violence to seize territory,  a process seemingly enabled by radical elements in Netanyahu’s governmentThe attack in Ein Arik came in the middle of the night and ",
            "isNew": true
          },
          {
            "title": "Iran’s Strikes on Ships in Strait of Hormuz Threaten Oil Flow",
            "link": "https://www.nytimes.com/2026/07/07/world/middleeast/iran-war-oman-hormuz-tanker.html",
            "source": "nytimes",
            "sources": [
              "nytimes"
            ],
            "pubDate": "Tue, 07 Jul 2026 22:01:00 +0000",
            "snippet": "The strikes by Iran and the attacks and re-imposition of sanctions by the U.S. came weeks after the countries agreed to try to find a lasting end to their hostilities.",
            "isNew": true
          },
          {
            "title": "US launches ​strikes against Iran after attacks on vessels in strait ​of ​Hormuz",
            "link": "https://www.theguardian.com/world/2026/jul/07/qatar-says-iran-fully-responsible-after-tankers-struck-in-strait-of-hormuz",
            "source": "guardian",
            "sources": [
              "guardian"
            ],
            "pubDate": "Tue, 07 Jul 2026 21:58:51 GMT",
            "snippet": "US Central Command says Tehran in ‘clear violation’ of ceasefire with ‘unwarranted’ ​attacks on commercial shipsMiddle East crisis – latest updatesThe US military launched ⁠a ⁠series of “powerful” ​st",
            "isNew": true
          }
        ]
      },
      {
        "category_id": "diplomacy",
        "category_name": "외교/협상",
        "category_icon": "🤝",
        "count": 6,
        "new_count": 6,
        "articles": [
          {
            "title": "Five key takeaways from the NATO summit in Ankara",
            "link": "https://www.aljazeera.com/news/2026/7/8/five-key-takeaways-from-the-nato-summit-in-ankara?traffic_source=rss",
            "source": "aljazeera",
            "sources": [
              "aljazeera"
            ],
            "pubDate": "Wed, 08 Jul 2026 19:06:35 +0000",
            "snippet": "Trump dominates summit with anti-Europe and Iran diatribes as NATO pledges to expand defence budgets and Ukraine support",
            "isNew": true
          },
          {
            "title": "US and Iran threaten return to war after fiercest exchange of fire since truce",
            "link": "https://www.theguardian.com/world/2026/jul/08/iran-us-war-ceasefire-peace-agreement-strikes-strait-of-hormuz",
            "source": "guardian",
            "sources": [
              "guardian"
            ],
            "pubDate": "Wed, 08 Jul 2026 18:32:47 GMT",
            "snippet": "Ceasefire appears close to collapse as two militaries target each other after after Iran strikes three commercial vesselsIran and the US have threatened to reignite their conflict after the most exten",
            "isNew": true
          },
          {
            "title": "Oil for unity: What is the US mediation plan in Libya?",
            "link": "https://www.aljazeera.com/news/2026/7/8/oil-for-unity-what-is-the-us-mediation-plan-in-libya?traffic_source=rss",
            "source": "aljazeera",
            "sources": [
              "aljazeera"
            ],
            "pubDate": "Wed, 08 Jul 2026 16:04:52 +0000",
            "snippet": "The plan, led by Trump relative Massad Boulos, promises oil investments if rival factions work together. ",
            "isNew": true
          },
          {
            "title": "Germany urges US-Iran negotiations, offers to minesweep Hormuz",
            "link": "https://www.aljazeera.com/video/newsfeed/2026/7/8/germany-urges-us-iran-negotiations-offers-to-minesweep-hormuz?traffic_source=rss",
            "source": "aljazeera",
            "sources": [
              "aljazeera"
            ],
            "pubDate": "Wed, 08 Jul 2026 15:57:41 +0000",
            "snippet": "German Foreign Minister Johann Wadephul urged the US and Iran to resume negotiations.",
            "isNew": true
          },
          {
            "title": "Bowen: For all his bluster, Trump has no better option than talks with Iran",
            "link": "https://www.bbc.co.uk/news/articles/cy8we3j14ndo?at_medium=RSS&at_campaign=rss",
            "source": "bbc",
            "sources": [
              "bbc"
            ],
            "pubDate": "Wed, 08 Jul 2026 15:30:00 GMT",
            "snippet": "The negotiating process is fragile and recent US strikes show how hard it will be to reach agreement, writes BBC's International Editor Jeremy Bowen. ",
            "isNew": true
          },
          {
            "title": "Trump declares ceasefire with Iran over during angry broadside at Nato summit",
            "link": "https://www.theguardian.com/world/2026/jul/08/trump-declares-ceasefire-iran-over-broadside-nato-summit",
            "source": "guardian",
            "sources": [
              "guardian"
            ],
            "pubDate": "Wed, 08 Jul 2026 11:50:36 GMT",
            "snippet": "President calls Iranian leadership ‘scum’, rails against alliance, repeats demand for Greenland and threatens SpainMiddle East crisis live – latest updatesEurope live – latest updatesDonald Trump has ",
            "isNew": true
          }
        ]
      },
      {
        "category_id": "economy",
        "category_name": "경제 영향",
        "category_icon": "📊",
        "count": 6,
        "new_count": 6,
        "articles": [
          {
            "title": "Trump says US ‘may take over Kharg Island’: Here’s what you need to know",
            "link": "https://www.aljazeera.com/news/2026/7/8/trump-says-us-may-take-over-kharg-island-heres-what-you-need-to-know?traffic_source=rss",
            "source": "aljazeera",
            "sources": [
              "aljazeera"
            ],
            "pubDate": "Wed, 08 Jul 2026 18:52:13 +0000",
            "snippet": "Kharg Island, pivotal to Iran&#039;s oil exports, becomes focal point as Trump renews threats amid rising Gulf tensions.",
            "isNew": true
          },
          {
            "title": "Oil Market Calm Shattered by Fresh Hostilities Between US and Iran",
            "link": "https://www.nytimes.com/2026/07/08/business/energy-environment/iran-war-oil-prices.html",
            "source": "nytimes",
            "sources": [
              "nytimes"
            ],
            "pubDate": "Wed, 08 Jul 2026 18:45:17 +0000",
            "snippet": "Oil prices are likely to remain volatile as long as the United States and Iran are unable to resolve the status of the Strait of Hormuz.",
            "isNew": true
          },
          {
            "title": "The Strait of Hormuz is now at the centre of Iranian and US calculus",
            "link": "https://www.aljazeera.com/opinions/2026/7/8/the-strait-of-hormuz-is-now-at-the-centre-of-iranian-and-us-calculus?traffic_source=rss",
            "source": "aljazeera",
            "sources": [
              "aljazeera"
            ],
            "pubDate": "Wed, 08 Jul 2026 16:48:31 +0000",
            "snippet": "The fate of the strait is directly linked to what happens next to the world economy.",
            "isNew": true
          },
          {
            "title": "Trump’s Iran strike comments shake markets, Brent crude hits two-week high",
            "link": "https://www.aljazeera.com/economy/2026/7/8/trumps-iran-strike-comments-shake-markets-brent-crude-hits-two-week-high?traffic_source=rss",
            "source": "aljazeera",
            "sources": [
              "aljazeera"
            ],
            "pubDate": "Wed, 08 Jul 2026 15:53:23 +0000",
            "snippet": "Travel stocks plunged as fuel costs rise, United Airlines fell 3 percent, while energy stocks saw gains.",
            "isNew": true
          },
          {
            "title": "IMF upgrades UK growth forecast as fears over impact of Iran war diminish",
            "link": "https://www.theguardian.com/business/2026/jul/08/imf-upgrades-uk-growth-forecast-as-fears-over-impact-of-iran-war-diminish",
            "source": "guardian",
            "sources": [
              "guardian"
            ],
            "pubDate": "Wed, 08 Jul 2026 13:00:32 GMT",
            "snippet": "July update projects GDP growth of 1% this year, making UK the third fastest-growing economy in the G7The International Monetary Fund (IMF) has upgraded its growth forecast for the UK, while leaving t",
            "isNew": true
          },
          {
            "title": "Iran’s holy city of Mashhad prepares for Khamenei’s burial.",
            "link": "https://www.nytimes.com/live/2026/07/08/world/iran-war-us-trump/irans-holy-city-of-mashhad-prepares-for-khameneis-burial",
            "source": "nytimes",
            "sources": [
              "nytimes"
            ],
            "pubDate": "Wed, 08 Jul 2026 11:03:09 +0000",
            "snippet": "As t",
            "isNew": true
          }
        ]
      },
      {
        "category_id": "humanitarian",
        "category_name": "인도주의/피해",
        "category_icon": "🏥",
        "count": 3,
        "new_count": 3,
        "articles": [
          {
            "title": "Israeli air strikes in Gaza kill eight, including two children",
            "link": "https://www.aljazeera.com/news/2026/7/8/israeli-air-strikes-in-gaza-kill-eight-including-two-children?traffic_source=rss",
            "source": "aljazeera",
            "sources": [
              "aljazeera"
            ],
            "pubDate": "Wed, 08 Jul 2026 18:35:11 +0000",
            "snippet": "Medics report 12 injuries alongside eight deaths in Gaza as Israeli air strikes target civilians and displaced families.",
            "isNew": true
          },
          {
            "title": "CCTV video shows Israeli border police officer throwing stun grenade into a car – video",
            "link": "https://www.theguardian.com/world/video/2026/jul/08/cctv-video-shows-israeli-border-police-officer-throwing-stun-grenade-into-a-car-video",
            "source": "guardian",
            "sources": [
              "guardian"
            ],
            "pubDate": "Wed, 08 Jul 2026 16:35:48 GMT",
            "snippet": "Israeli police have opened an investigation after CCTV footage showed a border police officer throwing a stun grenade into a car carrying young Palestinians during a raid on the Qalandiya refugee camp",
            "isNew": true
          },
          {
            "title": "Photo of bound Palestinian detainee corroborates Israeli torture reports, say rights groups",
            "link": "https://www.theguardian.com/world/2026/jul/08/photo-palestinian-prisoner-corroborates-israeli-torture-claims",
            "source": "guardian",
            "sources": [
              "guardian"
            ],
            "pubDate": "Wed, 08 Jul 2026 14:23:51 GMT",
            "snippet": "Image of man in underwear, blindfold and bound to iron rod has been widely shared on social mediaMiddle East crisis live – latest updatesAn Israeli soldier’s photo of a Palestinian man from Gaza strip",
            "isNew": true
          }
        ]
      },
      {
        "category_id": "other",
        "category_name": "기타",
        "category_icon": "📰",
        "count": 3,
        "new_count": 3,
        "articles": [
          {
            "title": "Atmosphere in Iran remains highly charged after Ayatollah’s funeral and escalation of grievances with US",
            "link": "https://www.theguardian.com/world/2026/jul/08/atmosphere-in-iran-remains-highly-charged-after-ayatollahs-funeral-and-escalation-of-grievances-with-us",
            "source": "guardian",
            "sources": [
              "guardian"
            ],
            "pubDate": "Wed, 08 Jul 2026 19:05:46 GMT",
            "snippet": "World is witnessing a turning point, says ministry spokesperson, as Iran seeks to assert independence amid rising tensionsBefore a foreign ministry press briefing at the Grand Hotel Tehran, the assemb",
            "isNew": true
          },
          {
            "title": "Lawyer says detained Gaza doctor was severely beaten in Israeli jail",
            "link": "https://www.bbc.co.uk/news/articles/c07yy3pgrlmo?at_medium=RSS&at_campaign=rss",
            "source": "bbc",
            "sources": [
              "bbc"
            ],
            "pubDate": "Tue, 07 Jul 2026 16:10:14 GMT",
            "snippet": "The lawyer for Dr Hussam Abu Safiya tells the BBC his client was so badly beaten he could not recognise him during a visit last week.",
            "isNew": true
          },
          {
            "title": "Life Support review – quietly devastating medics’ eye view of the war in Gaza",
            "link": "https://www.theguardian.com/film/2026/jul/07/life-support-review-medics-gaza-documentary",
            "source": "guardian",
            "sources": [
              "guardian"
            ],
            "pubDate": "Tue, 07 Jul 2026 08:00:34 GMT",
            "snippet": "In the absence of foreign media, doctors are valuable witnesses to the Israel-Hamas conflict in Daniele Rugo’s documentaryDying children and grieving parents are a fact of her work says Canadian paedi",
            "isNew": true
          }
        ]
      },
      {
        "category_id": "regional",
        "category_name": "지역 정세",
        "category_icon": "🌍",
        "count": 2,
        "new_count": 2,
        "articles": [
          {
            "title": "France returns Syrian artefacts it’s held since civil war",
            "link": "https://www.aljazeera.com/video/newsfeed/2026/7/8/france-returns-syrian-artefacts-its-held-since-civil-war?traffic_source=rss",
            "source": "aljazeera",
            "sources": [
              "aljazeera"
            ],
            "pubDate": "Wed, 08 Jul 2026 17:55:38 +0000",
            "snippet": "France has returned 23 Syrian antique artefacts it’s held since the outbreak of the 2011 civil war. ",
            "isNew": true
          },
          {
            "title": "Iran targets sites in Bahrain and Kuwait.",
            "link": "https://www.nytimes.com/live/2026/07/08/world/iran-war-us-trump/iran-targets-sites-in-bahrain-and-kuwait",
            "source": "nytimes",
            "sources": [
              "nytimes"
            ],
            "pubDate": "Wed, 08 Jul 2026 16:37:08 +0000",
            "snippet": "",
            "isNew": true
          }
        ]
      }
    ],
    "recent_30min": {
      "total_new": 50,
      "by_category": {
        "military": {
          "count": 12,
          "titles": [
            {
              "title": "Gaza’s World Cup screenings – in pictures",
              "link": "https://www.theguardian.com/world/gallery/2026/jul/08/gazas-world-cup-screenings-in-pictures",
              "source": "guardian"
            },
            {
              "title": "Iran Truce ‘Over,’ Trump Says, as He Threatens More Strikes",
              "link": "https://www.nytimes.com/2026/07/08/world/middleeast/iran-truce-trump.html",
              "source": "nytimes"
            },
            {
              "title": "Aid worker who organised World Cup screenings in Gaza killed in Israeli strike",
              "link": "https://www.theguardian.com/world/2026/jul/08/aid-worker-world-cup-screenings-gaza-killed-israeli-strike",
              "source": "guardian"
            },
            {
              "title": "NATO pledges 70 billion euros for Ukraine as Trump praises peace ‘progress’",
              "link": "https://www.aljazeera.com/news/2026/7/8/nato-pledges-70-billion-euros-for-ukraine-as-trump-praises-peace-progress?traffic_source=rss",
              "source": "aljazeera"
            },
            {
              "title": "Pakistan military says 42 killed in fighter attacks in Balochistan",
              "link": "https://www.aljazeera.com/news/2026/7/8/pakistan-military-says-42-killed-in-fighter-attacks-in-balochistan?traffic_source=rss",
              "source": "aljazeera"
            }
          ]
        },
        "politics": {
          "count": 18,
          "titles": [
            {
              "title": "In Israel, Rahm Emanuel Calls for End of Unconditional U.S. Support",
              "link": "https://www.nytimes.com/2026/07/07/us/politics/rahm-emanuel-speech-israel.html",
              "source": "nytimes"
            },
            {
              "title": "Iraqis Turn Out in Droves to Mourn Khamenei and Show Solidarity",
              "link": "https://www.nytimes.com/2026/07/08/world/middleeast/iraq-funeral-ayatollah-khamenei.html",
              "source": "nytimes"
            },
            {
              "title": "The Symbols We Saw at Khamenei’s Funeral",
              "link": "https://www.nytimes.com/video/world/middleeast/100000011012446/the-symbols-we-saw-at-khameneis-funeral.html",
              "source": "nytimes"
            },
            {
              "title": "As U.S.-Iran Cease-Fire Frays, Trump Faces a Muddled War and Unpalatable Options",
              "link": "https://www.nytimes.com/2026/07/08/us/politics/trump-iran-war.html",
              "source": "nytimes"
            },
            {
              "title": "Sabre-rattling to ‘tremendous love’: erratic Trump dominates final hours of Nato summit",
              "link": "https://www.theguardian.com/world/2026/jul/08/erratic-trump-dominates-final-hours-nato-summit",
              "source": "guardian"
            }
          ]
        },
        "diplomacy": {
          "count": 6,
          "titles": [
            {
              "title": "Five key takeaways from the NATO summit in Ankara",
              "link": "https://www.aljazeera.com/news/2026/7/8/five-key-takeaways-from-the-nato-summit-in-ankara?traffic_source=rss",
              "source": "aljazeera"
            },
            {
              "title": "US and Iran threaten return to war after fiercest exchange of fire since truce",
              "link": "https://www.theguardian.com/world/2026/jul/08/iran-us-war-ceasefire-peace-agreement-strikes-strait-of-hormuz",
              "source": "guardian"
            },
            {
              "title": "Oil for unity: What is the US mediation plan in Libya?",
              "link": "https://www.aljazeera.com/news/2026/7/8/oil-for-unity-what-is-the-us-mediation-plan-in-libya?traffic_source=rss",
              "source": "aljazeera"
            },
            {
              "title": "Germany urges US-Iran negotiations, offers to minesweep Hormuz",
              "link": "https://www.aljazeera.com/video/newsfeed/2026/7/8/germany-urges-us-iran-negotiations-offers-to-minesweep-hormuz?traffic_source=rss",
              "source": "aljazeera"
            },
            {
              "title": "Bowen: For all his bluster, Trump has no better option than talks with Iran",
              "link": "https://www.bbc.co.uk/news/articles/cy8we3j14ndo?at_medium=RSS&at_campaign=rss",
              "source": "bbc"
            }
          ]
        },
        "other": {
          "count": 3,
          "titles": [
            {
              "title": "Atmosphere in Iran remains highly charged after Ayatollah’s funeral and escalation of grievances with US",
              "link": "https://www.theguardian.com/world/2026/jul/08/atmosphere-in-iran-remains-highly-charged-after-ayatollahs-funeral-and-escalation-of-grievances-with-us",
              "source": "guardian"
            },
            {
              "title": "Lawyer says detained Gaza doctor was severely beaten in Israeli jail",
              "link": "https://www.bbc.co.uk/news/articles/c07yy3pgrlmo?at_medium=RSS&at_campaign=rss",
              "source": "bbc"
            },
            {
              "title": "Life Support review – quietly devastating medics’ eye view of the war in Gaza",
              "link": "https://www.theguardian.com/film/2026/jul/07/life-support-review-medics-gaza-documentary",
              "source": "guardian"
            }
          ]
        },
        "economy": {
          "count": 6,
          "titles": [
            {
              "title": "Trump says US ‘may take over Kharg Island’: Here’s what you need to know",
              "link": "https://www.aljazeera.com/news/2026/7/8/trump-says-us-may-take-over-kharg-island-heres-what-you-need-to-know?traffic_source=rss",
              "source": "aljazeera"
            },
            {
              "title": "Oil Market Calm Shattered by Fresh Hostilities Between US and Iran",
              "link": "https://www.nytimes.com/2026/07/08/business/energy-environment/iran-war-oil-prices.html",
              "source": "nytimes"
            },
            {
              "title": "The Strait of Hormuz is now at the centre of Iranian and US calculus",
              "link": "https://www.aljazeera.com/opinions/2026/7/8/the-strait-of-hormuz-is-now-at-the-centre-of-iranian-and-us-calculus?traffic_source=rss",
              "source": "aljazeera"
            },
            {
              "title": "Trump’s Iran strike comments shake markets, Brent crude hits two-week high",
              "link": "https://www.aljazeera.com/economy/2026/7/8/trumps-iran-strike-comments-shake-markets-brent-crude-hits-two-week-high?traffic_source=rss",
              "source": "aljazeera"
            },
            {
              "title": "IMF upgrades UK growth forecast as fears over impact of Iran war diminish",
              "link": "https://www.theguardian.com/business/2026/jul/08/imf-upgrades-uk-growth-forecast-as-fears-over-impact-of-iran-war-diminish",
              "source": "guardian"
            }
          ]
        },
        "humanitarian": {
          "count": 3,
          "titles": [
            {
              "title": "Israeli air strikes in Gaza kill eight, including two children",
              "link": "https://www.aljazeera.com/news/2026/7/8/israeli-air-strikes-in-gaza-kill-eight-including-two-children?traffic_source=rss",
              "source": "aljazeera"
            },
            {
              "title": "CCTV video shows Israeli border police officer throwing stun grenade into a car – video",
              "link": "https://www.theguardian.com/world/video/2026/jul/08/cctv-video-shows-israeli-border-police-officer-throwing-stun-grenade-into-a-car-video",
              "source": "guardian"
            },
            {
              "title": "Photo of bound Palestinian detainee corroborates Israeli torture reports, say rights groups",
              "link": "https://www.theguardian.com/world/2026/jul/08/photo-palestinian-prisoner-corroborates-israeli-torture-claims",
              "source": "guardian"
            }
          ]
        },
        "regional": {
          "count": 2,
          "titles": [
            {
              "title": "France returns Syrian artefacts it’s held since civil war",
              "link": "https://www.aljazeera.com/video/newsfeed/2026/7/8/france-returns-syrian-artefacts-its-held-since-civil-war?traffic_source=rss",
              "source": "aljazeera"
            },
            {
              "title": "Iran targets sites in Bahrain and Kuwait.",
              "link": "https://www.nytimes.com/live/2026/07/08/world/iran-war-us-trump/iran-targets-sites-in-bahrain-and-kuwait",
              "source": "nytimes"
            }
          ]
        }
      }
    }
  },
  "historical_comparison": [
    {
      "name": "걸프전 (1991)",
      "duration_days": 42,
      "type": "공습→지상전",
      "involved_countries": 35,
      "ended_by": "군사적 패배"
    },
    {
      "name": "이라크전 주요전투 (2003)",
      "duration_days": 42,
      "type": "침공",
      "involved_countries": 4,
      "ended_by": "정권 교체"
    },
    {
      "name": "2006 레바논 전쟁",
      "duration_days": 34,
      "type": "공습+지상전",
      "involved_countries": 2,
      "ended_by": "UN 휴전"
    },
    {
      "name": "2008 가자 전쟁",
      "duration_days": 22,
      "type": "공습→지상전",
      "involved_countries": 2,
      "ended_by": "일방적 휴전"
    },
    {
      "name": "2014 가자 전쟁",
      "duration_days": 50,
      "type": "공습+지상전",
      "involved_countries": 2,
      "ended_by": "협상 휴전"
    },
    {
      "name": "리비아 NATO 개입 (2011)",
      "duration_days": 222,
      "type": "공습 작전",
      "involved_countries": 18,
      "ended_by": "정권 교체"
    },
    {
      "name": "포클랜드 전쟁 (1982)",
      "duration_days": 74,
      "type": "해·공·지상전",
      "involved_countries": 2,
      "ended_by": "군사적 패배"
    },
    {
      "name": "코소보 NATO 폭격 (1999)",
      "duration_days": 78,
      "type": "공습 작전",
      "involved_countries": 19,
      "ended_by": "항복"
    },
    {
      "name": "이스라엘-하마스 (2023-25)",
      "duration_days": 470,
      "type": "공습+지상전",
      "involved_countries": 2,
      "ended_by": "협상 휴전"
    },
    {
      "name": "이란-이라크 전쟁 (1980-88)",
      "duration_days": 2922,
      "type": "총력전",
      "involved_countries": 2,
      "ended_by": "UN 휴전"
    },
    {
      "name": "러시아-우크라이나 전쟁 (2022-)",
      "duration_days": 1105,
      "type": "전면 침공+소모전",
      "involved_countries": 2,
      "ended_by": "진행 중"
    },
    {
      "name": "2025 이란-이스라엘 교전",
      "duration_days": 12,
      "type": "공습 작전",
      "involved_countries": 3,
      "ended_by": "중재 휴전"
    }
  ],
  "economic_indicators": {
    "WTI": {
      "price": 74.1,
      "change": 3.66,
      "changePercent": 5.2,
      "prev": 70.44
    },
    "BRENT": {
      "price": 78.54,
      "change": 4.38,
      "changePercent": 5.91,
      "prev": 74.16
    },
    "GOLD": {
      "price": 4090.3,
      "change": -55,
      "changePercent": -1.33,
      "prev": 4145.3
    },
    "US2Y": {
      "price": 3.72,
      "change": 0,
      "changePercent": 0,
      "prev": 3.72
    },
    "US10Y": {
      "price": 4.57,
      "change": 0.04,
      "changePercent": 0.88,
      "prev": 4.53
    },
    "VIX": {
      "price": 16.84,
      "change": 0.71,
      "changePercent": 4.4,
      "prev": 16.13
    },
    "DXY": {
      "price": 100.99,
      "change": -0.15,
      "changePercent": -0.15,
      "prev": 101.14
    }
  },
  "critical_events": [
    {
      "id": "regime_collapse",
      "name": "교전국 정권 붕괴/쿠데타",
      "severity": "critical",
      "confidence": 0.6666666666666666,
      "matchCount": 2,
      "direction": "shorten"
    },
    {
      "id": "unilateral_deescalation",
      "name": "일방적 전투 축소/자제 선언",
      "severity": "high",
      "confidence": 0.6666666666666666,
      "matchCount": 2,
      "direction": "shorten"
    },
    {
      "id": "capital_attack",
      "name": "수도 직접 공격/포위",
      "severity": "high",
      "confidence": 0.6666666666666666,
      "matchCount": 2,
      "direction": "shorten"
    }
  ],
  "feeds_loaded": 7,
  "feeds_total": 8
}