{
  "timestamp": "2026-03-16T20:35:36.417Z",
  "war_day": 16,
  "probabilities": {
    "1개월 내 (~3월)": 19,
    "2~3개월 (4~5월)": 38.1,
    "4~6개월 (6~8월)": 24.9,
    "7~12개월 (9월~27/2월)": 13.3,
    "1년 초과": 4.7
  },
  "factors": [
    {
      "factor": "트럼프 대통령 4-5주 예상 발언",
      "impact": "2~3개월 내 종전 확률 상승",
      "weight": "+8%p (2~3개월) (잔존30%)",
      "direction": "shorten",
      "detail": "트럼프 대통령이 공개적으로 전쟁이 \"4-5주 내\"에 끝날 것이라고 발언했습니다.",
      "keywords": [
        "trump",
        "4 week",
        "5 week",
        "timeline",
        "end war"
      ],
      "applied": "2026-03-01",
      "active": true,
      "decay": 0.3
    },
    {
      "factor": "이스라엘 제공권 장악 (이란 방공 80% 파괴)",
      "impact": "단기 종전 가능성 증가",
      "weight": "+4%p (1개월내), +6%p (2~3개월) (잔존68%)",
      "direction": "shorten",
      "detail": "이스라엘이 이란 방공망의 핵심을 무력화했습니다.",
      "keywords": [
        "air superi",
        "air defens",
        "s-300",
        "s-400",
        "radar",
        "anti-air"
      ],
      "applied": "2026-03-01",
      "active": true,
      "decay": 0.6828
    },
    {
      "factor": "확전 뉴스 우세 (확전6:휴전2)",
      "impact": "전쟁 장기화 가능성 (확전비율 75%)",
      "weight": "+0.03%p (4~6개월)",
      "direction": "lengthen",
      "detail": "언론에서 휴전보다 확전을 더 많이 보도하고 있습니다.",
      "keywords": [
        "escalat",
        "intensif",
        "expand",
        "widen"
      ],
      "applied": "실시간",
      "active": true,
      "decay": 1
    },
    {
      "factor": "호르무즈 해협 봉쇄 → 국제 경제 압력",
      "impact": "경제적 압력으로 빠른 해결 촉구",
      "weight": "+3%p (1개월내), +5%p (2~3개월) (잔존68%)",
      "direction": "shorten",
      "detail": "세계 원유의 약 20%가 호르무즈 해협을 통과합니다.",
      "keywords": [
        "hormuz",
        "strait",
        "oil price",
        "blockade",
        "shipping",
        "tanker"
      ],
      "applied": "2026-03-01",
      "active": true,
      "decay": 0.6828
    },
    {
      "factor": "9개국 참전 - 분쟁 복잡성 증가",
      "impact": "다자간 분쟁으로 협상 복잡화",
      "weight": "+5%p (4~6개월), +3%p (7~12개월) (잔존30%)",
      "direction": "lengthen",
      "detail": "참전국이 많을수록 휴전 협상이 복잡해집니다.",
      "keywords": [
        "coalition",
        "allies",
        "nato",
        "joint operation",
        "multinational"
      ],
      "applied": "2026-03-02",
      "active": true,
      "decay": 0.3
    },
    {
      "factor": "하메네이 사망 - 이란 지도부 공백",
      "impact": "정권 붕괴 가능성과 내부 혼란 장기화 위험",
      "weight": "+4%p (2~3개월), +4%p (4~6개월) (잔존31%)",
      "direction": "mixed",
      "detail": "최고지도자의 사망으로 정권 내부에 큰 혼란이 발생합니다.",
      "keywords": [
        "khamenei",
        "supreme leader",
        "succession",
        "leadership",
        "regime"
      ],
      "applied": "2026-03-03",
      "active": true,
      "decay": 0.3071
    },
    {
      "factor": "쿠르드족 지상군 이란 국경 진입",
      "impact": "지상전 확대로 전쟁 장기화 위험",
      "weight": "+4%p (4~6개월), +3%p (7~12개월) (잔존36%)",
      "direction": "lengthen",
      "detail": "쿠르드 페쉬메르가 부대가 북부 전선을 열었습니다.",
      "keywords": [
        "kurd",
        "peshmerga",
        "ground",
        "border",
        "northern front"
      ],
      "applied": "2026-03-04",
      "active": true,
      "decay": 0.3571
    },
    {
      "factor": "이란 3/5 CIA 통한 협상 시도",
      "impact": "이란의 협상 의지 → 단기 종전 가능성 증가",
      "weight": "+5%p (1개월내), +8%p (2~3개월) (잔존41%)",
      "direction": "shorten",
      "detail": "이란이 비밀 채널을 통해 협상을 시도했습니다.",
      "keywords": [
        "cia",
        "backchannel",
        "secret talk",
        "negotiat",
        "iran offer",
        "surrender"
      ],
      "applied": "2026-03-05",
      "active": true,
      "decay": 0.4071
    },
    {
      "factor": "걸프전(42일) 패턴 유사성",
      "impact": "제공권→지상작전→빠른 종결 패턴",
      "weight": "참고: 걸프전 42일, 코소보 78일, 포클랜드 74일",
      "direction": "reference",
      "detail": "이번 전쟁은 걸프전과 매우 유사한 패턴을 보입니다.",
      "keywords": [
        "gulf war",
        "desert storm",
        "pattern",
        "historical"
      ],
      "applied": "2026-02-28",
      "active": true,
      "decay": 1
    },
    {
      "factor": "협상/외교 뉴스 8건 감지",
      "impact": "외교적 해결 움직임 포착",
      "weight": "+0.02%p (1개월내), +0.01%p (2~3개월)",
      "direction": "shorten",
      "detail": "실시간 뉴스에서 협상 관련 기사 8건이 감지되었습니다.",
      "keywords": [
        "negotiat",
        "talks",
        "dialog",
        "diplomat",
        "mediati"
      ],
      "applied": "실시간",
      "active": true,
      "decay": 1
    },
    {
      "factor": "지역 확산 뉴스 22.2건 감지",
      "impact": "주변국 대규모 연루 → 장기화 위험 높음",
      "weight": "+0.02%p (4~6개월), +0.02%p (7~12개월)",
      "direction": "lengthen",
      "detail": "주변국을 언급하는 기사 22.2건이 감지되었습니다.",
      "keywords": [
        "saudi",
        "uae",
        "qatar",
        "iraq",
        "lebanon",
        "turkey"
      ],
      "applied": "실시간",
      "active": true,
      "decay": 1
    },
    {
      "factor": "미 상원 전쟁 결의안 부결",
      "impact": "미국 내 정치적 지지로 군사작전 지속 가능",
      "weight": "+3%p (2~3개월), +2%p (4~6개월) (잔존36%)",
      "direction": "mixed",
      "detail": "미 상원이 전쟁권한 제한 결의안을 부결시켰습니다.",
      "keywords": [
        "senate",
        "resolution",
        "war powers",
        "congress",
        "vote"
      ],
      "applied": "2026-03-04",
      "active": true,
      "decay": 0.3571
    },
    {
      "factor": "사우디/UAE 연합군 참전",
      "impact": "이란 포위망 강화 → 조기 항복 가능성",
      "weight": "+3%p (1개월내), +5%p (2~3개월) (잔존31%)",
      "direction": "shorten",
      "detail": "사우디와 UAE가 연합군에 합류했습니다.",
      "keywords": [
        "saudi",
        "uae",
        "coalition",
        "join",
        "alliance",
        "gcc"
      ],
      "applied": "2026-03-03",
      "active": true,
      "decay": 0.3071
    },
    {
      "factor": "[중대 이벤트] 수도 직접 공격/포위",
      "impact": "수도 직접 공격. 베오그라드(1999): 78일 폭격 후 항복. 바그다드(2003): 21일만에 함락. 수도 타격은 전쟁 지속 의지를 급격히 약화.",
      "weight": "+4.0%p (1개월내), +6.0%p (2~3개월), -2.0%p (4~6개월), -2.0%p (7~12개월), -1.0%p (1년초과)",
      "direction": "shorten",
      "detail": "수도 직접 공격. 베오그라드(1999): 78일 폭격 후 항복. 바그다드(2003): 21일만에 함락. 수도 타격은 전쟁 지속 의지를 급격히 약화.\n\n신뢰도: 확실 (100%), 관련 기사 4건 감지.\n관련: Civilians pulled from rubble after US-Israeli strikes on Tehran | In maps: Attacks across Iran and the Middle East enter third week",
      "keywords": [
        "capital",
        "bomb",
        "capital",
        "strike",
        "capital",
        "attack",
        "capital",
        "siege",
        "capital",
        "pound",
        "capital",
        "explosion",
        "tehran",
        "bomb",
        "tehran",
        "strike",
        "tehran",
        "pound",
        "tehran",
        "explosion"
      ],
      "applied": "2026-03-16",
      "active": true,
      "severity": "high"
    },
    {
      "factor": "[중대 이벤트] 전선 확대/신규 참전국",
      "impact": "분쟁 확대 또는 신규 참전. 역사적으로 참전국 1개 추가 시 평균 전쟁 기간 30~50% 증가 (Correlates of War 데이터).",
      "weight": "-1.3%p (1개월내), -2.0%p (2~3개월), +2.7%p (4~6개월), +2.0%p (7~12개월), +1.3%p (1년초과)",
      "direction": "lengthen",
      "detail": "분쟁 확대 또는 신규 참전. 역사적으로 참전국 1개 추가 시 평균 전쟁 기간 30~50% 증가 (Correlates of War 데이터).\n\n신뢰도: 높음 (67%), 관련 기사 2건 감지.\n관련: In maps: Attacks across Iran and the Middle East enter third week",
      "keywords": [
        "new front",
        "war spread",
        "conflict expand",
        "join",
        "war",
        "enter",
        "war",
        "open",
        "front",
        "declare war",
        "widen",
        "conflict",
        "second front",
        "new theater"
      ],
      "applied": "2026-03-16",
      "active": true,
      "severity": "moderate"
    },
    {
      "factor": "유가 급등 (WTI $93.75/배럴)",
      "impact": "중간 수준 경제 압력",
      "weight": "+2%p (1-2개월)",
      "direction": "shorten",
      "detail": "WTI 유가가 $93.75/배럴로 90달러 이상입니다. 호르무즈 해협 봉쇄와 맞물려 글로벌 에너지 시장에 큰 충격을 주고 있으며, 주요국들의 조기 종전 압력이 강화되고 있습니다.",
      "keywords": [
        "oil",
        "crude",
        "wti",
        "brent",
        "energy",
        "gas price"
      ],
      "applied": "실시간",
      "active": true
    },
    {
      "factor": "금값 사상최고 ($5022.1/oz)",
      "impact": "안전자산 수요 폭증 → 글로벌 불안 심화",
      "weight": "+2%p (4-6개월)",
      "direction": "lengthen",
      "detail": "금 가격이 온스당 $5022.1로 사상 최고 수준입니다. 투자자들이 안전자산으로 대거 이동하고 있으며, 이는 전쟁 장기화에 대한 시장의 우려를 반영합니다.",
      "keywords": [
        "gold",
        "safe haven",
        "precious metal",
        "investor"
      ],
      "applied": "실시간",
      "active": true
    }
  ],
  "news_signals": {
    "ceasefire_mentions": 2,
    "escalation_mentions": 6,
    "negotiation_mentions": 8,
    "casualty_mentions": 4.2,
    "peace_mentions": 4,
    "regional_spread": 22.2,
    "total_articles": 50,
    "new_articles": 50,
    "unique_events": 46,
    "duplicates_removed": 4
  },
  "latest_news": [
    {
      "title": "Middle East crisis live: Trump vents frustration with allies as European countries resist demand for help in strait of Hormuz",
      "link": "https://www.theguardian.com/world/live/2026/mar/16/iran-war-live-updates-news-oil-trump-hormuz-dubai-airport-israel-targets",
      "pubDate": "Mon, 16 Mar 2026 20:33:49 GMT",
      "source": "guardian",
      "snippet": "US president lashes out at UK and others as European countries reject calls for assistance to reopen crucial shipping laneEuropean countries reject Trump’s call for help to reopen strait of HormuzHow ",
      "isNew": true,
      "_sourceCount": 2,
      "_isDuplicated": true,
      "_clusterSize": 2,
      "_isDuplicate": false
    },
    {
      "title": "Gulf states may be covertly encouraging attacks by US, Iran foreign minister says",
      "link": "https://www.theguardian.com/world/2026/mar/16/gulf-states-may-be-covertly-encouraging-attacks-by-us-irans-foreign-minister-says",
      "pubDate": "Mon, 16 Mar 2026 20:27:51 GMT",
      "source": "guardian",
      "snippet": "Abbas Araghchi demands clarification on reports Saudi crown prince urged Donald Trump to ‘hit the Iranians hard’Middle East crisis – live updatesSome Gulf states hosting US forces may be covertly enco",
      "isNew": true,
      "_sourceCount": 1,
      "_isDuplicated": false,
      "_clusterSize": 1,
      "_isDuplicate": false
    },
    {
      "title": "Hezbollah rocket hits a residential building in Israel’s Nahariya",
      "link": "https://www.aljazeera.com/video/newsfeed/2026/3/16/hezbollah-rocket-hits-a-residential-building-in-israels-nahariya?traffic_source=rss",
      "pubDate": "Mon, 16 Mar 2026 20:27:10 +0000",
      "source": "aljazeera",
      "snippet": "Firefighters battled a blaze at a residential building in Nahariya, Israel after a Hezbollah rocket hit it.",
      "isNew": true,
      "_sourceCount": 1,
      "_isDuplicated": false,
      "_clusterSize": 1,
      "_isDuplicate": false
    },
    {
      "title": "서방 5개국 \"레바논서 이스라엘-헤즈볼라 적대행위 중단해야\"",
      "link": "https://www.yna.co.kr/view/AKR20260317007800072",
      "pubDate": "Tue, 17 Mar 2026 05:25:43 +0900",
      "source": "yonhap",
      "snippet": "(뉴욕=연합뉴스) 이지헌 특파원 = 캐나다와 프랑스, 독일, 이탈리아, 영국 정상이 16일(현지시간) 레바논에서 이스라엘의 지상군 공세가 참혹한...",
      "isNew": true,
      "_sourceCount": 1,
      "_isDuplicated": false,
      "_clusterSize": 1,
      "_isDuplicate": false
    },
    {
      "title": "What Are Trump’s Positions on Iran? They Can Change by the Sentence.",
      "link": "https://www.nytimes.com/2026/03/16/us/politics/trump-iran-war.html",
      "pubDate": "Mon, 16 Mar 2026 20:14:51 +0000",
      "source": "nytimes",
      "snippet": "The president is no stranger to staking out contradictory stands, part of what his aides say is his negotiating style. But on Iran, his shifting positions are colliding with the consequences of war.",
      "isNew": true,
      "_sourceCount": 1,
      "_isDuplicated": false,
      "_clusterSize": 1,
      "_isDuplicate": false
    },
    {
      "title": "European countries reject Trump’s call for help to reopen strait of Hormuz",
      "link": "https://www.theguardian.com/world/2026/mar/16/europe-donald-trump-strait-hormuz-iran",
      "pubDate": "Mon, 16 Mar 2026 19:30:43 GMT",
      "source": "guardian",
      "snippet": "Leaders seek a diplomatic solution despite US president’s threat of ‘a very bad future’ for Nato unless it provides warshipsMiddle East crisis – live updatesEuropean countries have ruled out sending w",
      "isNew": true,
      "_sourceCount": 1,
      "_isDuplicated": false,
      "_clusterSize": 1,
      "_isDuplicate": false
    },
    {
      "title": "Starmer distances UK from Iran war as EU leaders rule out sending warships",
      "link": "https://www.theguardian.com/world/2026/mar/16/starmer-distances-uk-from-iran-war-as-eu-leaders-rule-out-sending-warships",
      "pubDate": "Mon, 16 Mar 2026 19:29:20 GMT",
      "source": "guardian",
      "snippet": "PM refuses to be drawn into wider conflict as Germany and Italy defy Trump’s call to help reopen strait of HormuzMiddle East crisis – live updatesKeir Starmer has insisted that the UK will not be draw",
      "isNew": true,
      "_sourceCount": 1,
      "_isDuplicated": false,
      "_clusterSize": 1,
      "_isDuplicate": false
    },
    {
      "title": "Israeli forces in southern Lebanon as ground operation announced",
      "link": "https://www.aljazeera.com/video/newsfeed/2026/3/16/israeli-forces-in-southern-lebanon-as-ground-operation-announced?traffic_source=rss",
      "pubDate": "Mon, 16 Mar 2026 19:14:42 +0000",
      "source": "aljazeera",
      "snippet": "Israeli forces attacked multiple towns in southern Lebanon after announcing “limited and targeted ground operations.&quot;",
      "isNew": true,
      "_sourceCount": 1,
      "_isDuplicated": false,
      "_clusterSize": 1,
      "_isDuplicate": false
    },
    {
      "title": "Israel’s Expanding Ground Assault in Lebanon Meets Resistance in Hilltop Town",
      "link": "https://www.nytimes.com/2026/03/16/world/middleeast/lebanon-strategic-town-khiam.html",
      "pubDate": "Mon, 16 Mar 2026 18:53:51 +0000",
      "source": "nytimes",
      "snippet": "The town of Khiam’s location on high ground just a few miles north of the border between Israel and Lebanon has made it coveted territory over multiple conflicts.",
      "isNew": true,
      "_sourceCount": 1,
      "_isDuplicated": false,
      "_clusterSize": 1,
      "_isDuplicate": false
    },
    {
      "title": "Trump says Hormuz Strait help ‘on the way’ as allies reject military action",
      "link": "https://www.aljazeera.com/news/2026/3/16/trump-says-hormuz-strait-help-on-the-way-as-allies-reject-military-action?traffic_source=rss",
      "pubDate": "Mon, 16 Mar 2026 18:53:32 +0000",
      "source": "aljazeera",
      "snippet": "US president refuses to identify which countries he says are responding to call for naval coalition to open trade route.",
      "isNew": true,
      "_isDuplicate": true,
      "_sourceCount": 1
    },
    {
      "title": "Sri Lanka brings in four-day week to eke out stocks of oil and gas hit by Iran war",
      "link": "https://www.theguardian.com/world/2026/mar/16/sri-lanka-four-day-week-oil-and-gas-iran-war",
      "pubDate": "Mon, 16 Mar 2026 18:52:04 GMT",
      "source": "guardian",
      "snippet": "Effective closure of strait of Hormuz also affecting Bangladesh, India and Pakistan, which have brought in crisis measuresSri Lanka is introducing a shorter four-day working week to preserve its shrin",
      "isNew": true,
      "_sourceCount": 1,
      "_isDuplicated": false,
      "_clusterSize": 1,
      "_isDuplicate": false
    },
    {
      "title": "Fifth Member of Iranian Soccer Team Reverses Decision on Asylum",
      "link": "https://www.nytimes.com/2026/03/16/world/middleeast/iran-soccer-team-asylum-australia.html",
      "pubDate": "Mon, 16 Mar 2026 18:41:26 +0000",
      "source": "nytimes",
      "snippet": "Five of the seven members of the Iranian women’s national team who originally sought asylum in Australia after a tournament have changed their minds.",
      "isNew": true,
      "_sourceCount": 1,
      "_isDuplicated": false,
      "_clusterSize": 1,
      "_isDuplicate": false
    },
    {
      "title": "The Guardian view on Trump’s war with Iran: if the US is winning, why ask Nato for help? | Editorial",
      "link": "https://www.theguardian.com/commentisfree/2026/mar/16/the-guardian-view-on-trumps-war-with-iran-if-the-us-is-winning-why-ask-nato-for-help",
      "pubDate": "Mon, 16 Mar 2026 18:41:09 GMT",
      "source": "guardian",
      "snippet": "The US has overwhelming military power. Yet the battle has moved to oil routes, alliances and domestic politics – where Tehran is testing western unityDonald Trump would like you to know that he is wi",
      "isNew": true,
      "_sourceCount": 1,
      "_isDuplicated": false,
      "_clusterSize": 1,
      "_isDuplicate": false
    },
    {
      "title": "In Choosing ‘Epic Fury,’ Trump Names a War and Defines His Presidency",
      "link": "https://www.nytimes.com/2026/03/16/us/politics/trump-operation-epic-fury-anger.html",
      "pubDate": "Mon, 16 Mar 2026 18:36:39 +0000",
      "source": "nytimes",
      "snippet": "The branding of the U.S. military operation against Iran is a quintessentially Trumpian choice for a leader whose tenure has been marked by anger.",
      "isNew": true,
      "_sourceCount": 1,
      "_isDuplicated": false,
      "_clusterSize": 1,
      "_isDuplicate": false
    },
    {
      "title": "Israel’s plan to expand Lebanon ground campaign fuels fears of prolonged occupation",
      "link": "https://www.theguardian.com/world/2026/mar/16/israel-expansion-lebanon-ground-campaign-fears-prolonged-occupation",
      "pubDate": "Mon, 16 Mar 2026 18:31:52 GMT",
      "source": "guardian",
      "snippet": "Israeli defence minister says IDF instructed to destroy ‘terror infrastructure’ in southern villagesMiddle East crisis – live updatesIsrael’s announcement on Monday of a ground campaign in new areas o",
      "isNew": true,
      "_sourceCount": 1,
      "_isDuplicated": false,
      "_clusterSize": 1,
      "_isDuplicate": false
    }
  ],
  "news_digest": {
    "categories": [
      {
        "category_id": "military",
        "category_name": "군사 작전",
        "category_icon": "⚔️",
        "count": 11,
        "new_count": 11,
        "articles": [
          {
            "title": "Hezbollah rocket hits a residential building in Israel’s Nahariya",
            "link": "https://www.aljazeera.com/video/newsfeed/2026/3/16/hezbollah-rocket-hits-a-residential-building-in-israels-nahariya?traffic_source=rss",
            "source": "aljazeera",
            "sources": [
              "aljazeera"
            ],
            "pubDate": "Mon, 16 Mar 2026 20:27:10 +0000",
            "snippet": "Firefighters battled a blaze at a residential building in Nahariya, Israel after a Hezbollah rocket hit it.",
            "isNew": true
          },
          {
            "title": "Israeli forces in southern Lebanon as ground operation announced",
            "link": "https://www.aljazeera.com/video/newsfeed/2026/3/16/israeli-forces-in-southern-lebanon-as-ground-operation-announced?traffic_source=rss",
            "source": "aljazeera",
            "sources": [
              "aljazeera"
            ],
            "pubDate": "Mon, 16 Mar 2026 19:14:42 +0000",
            "snippet": "Israeli forces attacked multiple towns in southern Lebanon after announcing “limited and targeted ground operations.&quot;",
            "isNew": true
          },
          {
            "title": "The Guardian view on Trump’s war with Iran: if the US is winning, why ask Nato for help? | Editorial",
            "link": "https://www.theguardian.com/commentisfree/2026/mar/16/the-guardian-view-on-trumps-war-with-iran-if-the-us-is-winning-why-ask-nato-for-help",
            "source": "guardian",
            "sources": [
              "guardian"
            ],
            "pubDate": "Mon, 16 Mar 2026 18:41:09 GMT",
            "snippet": "The US has overwhelming military power. Yet the battle has moved to oil routes, alliances and domestic politics – where Tehran is testing western unityDonald Trump would like you to know that he is wi",
            "isNew": true
          },
          {
            "title": "In Choosing ‘Epic Fury,’ Trump Names a War and Defines His Presidency",
            "link": "https://www.nytimes.com/2026/03/16/us/politics/trump-operation-epic-fury-anger.html",
            "source": "nytimes",
            "sources": [
              "nytimes"
            ],
            "pubDate": "Mon, 16 Mar 2026 18:36:39 +0000",
            "snippet": "The branding of the U.S. military operation against Iran is a quintessentially Trumpian choice for a leader whose tenure has been marked by anger.",
            "isNew": true
          },
          {
            "title": "Israel’s plan to expand Lebanon ground campaign fuels fears of prolonged occupation",
            "link": "https://www.theguardian.com/world/2026/mar/16/israel-expansion-lebanon-ground-campaign-fears-prolonged-occupation",
            "source": "guardian",
            "sources": [
              "guardian"
            ],
            "pubDate": "Mon, 16 Mar 2026 18:31:52 GMT",
            "snippet": "Israeli defence minister says IDF instructed to destroy ‘terror infrastructure’ in southern villagesMiddle East crisis – live updatesIsrael’s announcement on Monday of a ground campaign in new areas o",
            "isNew": true
          },
          {
            "title": "US responsible for deadly attack on Iranian school: Amnesty International",
            "link": "https://www.aljazeera.com/news/2026/3/16/us-responsible-for-deadly-attack-on-iranian-school-amnesty-international?traffic_source=rss",
            "source": "aljazeera",
            "sources": [
              "aljazeera"
            ],
            "pubDate": "Mon, 16 Mar 2026 17:01:52 +0000",
            "snippet": "Rights group says Tomahawk missile likely used in Minab school strike that killed at least 170 people, mostly children.",
            "isNew": true
          },
          {
            "title": "In maps: Attacks across Iran and the Middle East enter third week",
            "link": "https://www.bbc.com/news/articles/c4g0pnnj8xyo?at_medium=RSS&at_campaign=rss",
            "source": "bbc",
            "sources": [
              "bbc"
            ],
            "pubDate": "Mon, 16 Mar 2026 16:21:47 GMT",
            "snippet": "The US-Israeli war with Iran has seen sustained attacks on Tehran and Beirut as  retaliatory strikes are felt in Israel and Gulf states",
            "isNew": true
          },
          {
            "title": "Israel Denies That It Is Running Out of Missile Interceptors",
            "link": "https://www.nytimes.com/2026/03/16/world/middleeast/israel-interceptors.html",
            "source": "nytimes",
            "sources": [
              "nytimes"
            ],
            "pubDate": "Mon, 16 Mar 2026 14:20:06 +0000",
            "snippet": "Israeli military says it had prepared for a prolonged conflict after a news report said its supplies of ballistic missile interceptors were running “critically low.”",
            "isNew": true
          },
          {
            "title": "US says it has destroyed Iran missile capacity: How is Iran still shooting?",
            "link": "https://www.aljazeera.com/news/2026/3/16/us-says-it-has-destroyed-iran-missile-capacity-how-is-iran-still-shooting?traffic_source=rss",
            "source": "aljazeera",
            "sources": [
              "aljazeera"
            ],
            "pubDate": "Mon, 16 Mar 2026 14:08:43 +0000",
            "snippet": "Despite degraded launch capabilities, Iran has enough missiles to fire strategically, keep region on edge, say experts.",
            "isNew": true
          },
          {
            "title": "Qatar calls on Iran to stop Gulf attacks, urges diplomatic solution",
            "link": "https://www.aljazeera.com/news/2026/3/16/qatar-calls-on-iran-to-stop-gulf-attacks-urges-diplomatic-solution?traffic_source=rss",
            "source": "aljazeera",
            "sources": [
              "aljazeera"
            ],
            "pubDate": "Mon, 16 Mar 2026 14:07:14 +0000",
            "snippet": "Qatar foreign ministry spokesman Majed al-Ansari accuses Iran of targeting civilian areas as he calls for de-escalation.",
            "isNew": true
          }
        ]
      },
      {
        "category_id": "economy",
        "category_name": "경제 영향",
        "category_icon": "📊",
        "count": 11,
        "new_count": 11,
        "articles": [
          {
            "title": "Middle East crisis live: Trump vents frustration with allies as European countries resist demand for help in strait of Hormuz",
            "link": "https://www.theguardian.com/world/live/2026/mar/16/iran-war-live-updates-news-oil-trump-hormuz-dubai-airport-israel-targets",
            "source": "guardian",
            "sources": [
              "guardian",
              "aljazeera"
            ],
            "pubDate": "Mon, 16 Mar 2026 20:33:49 GMT",
            "snippet": "US president lashes out at UK and others as European countries reject calls for assistance to reopen crucial shipping laneEuropean countries reject Trump’s call for help to reopen strait of HormuzHow ",
            "isNew": true
          },
          {
            "title": "Starmer distances UK from Iran war as EU leaders rule out sending warships",
            "link": "https://www.theguardian.com/world/2026/mar/16/starmer-distances-uk-from-iran-war-as-eu-leaders-rule-out-sending-warships",
            "source": "guardian",
            "sources": [
              "guardian"
            ],
            "pubDate": "Mon, 16 Mar 2026 19:29:20 GMT",
            "snippet": "PM refuses to be drawn into wider conflict as Germany and Italy defy Trump’s call to help reopen strait of HormuzMiddle East crisis – live updatesKeir Starmer has insisted that the UK will not be draw",
            "isNew": true
          },
          {
            "title": "Sri Lanka brings in four-day week to eke out stocks of oil and gas hit by Iran war",
            "link": "https://www.theguardian.com/world/2026/mar/16/sri-lanka-four-day-week-oil-and-gas-iran-war",
            "source": "guardian",
            "sources": [
              "guardian"
            ],
            "pubDate": "Mon, 16 Mar 2026 18:52:04 GMT",
            "snippet": "Effective closure of strait of Hormuz also affecting Bangladesh, India and Pakistan, which have brought in crisis measuresSri Lanka is introducing a shorter four-day working week to preserve its shrin",
            "isNew": true
          },
          {
            "title": "IEA to consider release of more oil reserves as Iran war keeps prices high",
            "link": "https://www.theguardian.com/business/2026/mar/16/iea-release-oil-reserves-iran-war-prices-strait-of-hormuz",
            "source": "guardian",
            "sources": [
              "guardian"
            ],
            "pubDate": "Mon, 16 Mar 2026 17:51:21 GMT",
            "snippet": "Head of world’s energy watchdog says it will take time for markets to recover from ongoing crisis in strait of HormuzThe world’s energy watchdog will consider releasing further emergency crude stocks ",
            "isNew": true
          },
          {
            "title": "Could Trump blow up Nato over Iran war? – The Latest",
            "link": "https://www.theguardian.com/news/audio/2026/mar/16/could-trump-blow-up-nato-over-iran-war-the-latest",
            "source": "guardian",
            "sources": [
              "guardian",
              "aljazeera"
            ],
            "pubDate": "Mon, 16 Mar 2026 16:50:24 GMT",
            "snippet": "Donald Trump is pressuring European allies to protect the strait of Hormuz, warning that Nato faces a ‘very bad’ future if members fail to offer assistance.The strait of Hormuz is one of the most impo",
            "isNew": true
          },
          {
            "title": "How badly has the Iran war hit the global economy? The tell-tale signs",
            "link": "https://www.aljazeera.com/news/2026/3/16/the-tell-tale-signs-how-bad-has-the-iran-war-hit-the-global-economy?traffic_source=rss",
            "source": "aljazeera",
            "sources": [
              "aljazeera"
            ],
            "pubDate": "Mon, 16 Mar 2026 15:54:02 +0000",
            "snippet": "Oil and gas price hikes due to the war have rattled the global economy.",
            "isNew": true
          },
          {
            "title": "Iran’s Hormuz blockade is its most powerful card against Trump and Israel. It won’t back down easily | Jack Watling",
            "link": "https://www.theguardian.com/commentisfree/2026/mar/16/iran-strait-of-hormuz-blockade-trump-israel",
            "source": "guardian",
            "sources": [
              "guardian"
            ],
            "pubDate": "Mon, 16 Mar 2026 15:49:46 GMT",
            "snippet": "By imposing massive costs on the global economy, the Iranian government hopes to cause the US to back downThe US and Israeli decision to attack Iran has sent economic shockwaves around the world. Abou",
            "isNew": true
          },
          {
            "title": "Is Russia benefitting from the Iran war?",
            "link": "https://www.aljazeera.com/video/newsfeed/2026/3/16/is-russia-benefitting-from-the-iran-war?traffic_source=rss",
            "source": "aljazeera",
            "sources": [
              "aljazeera"
            ],
            "pubDate": "Mon, 16 Mar 2026 15:49:27 +0000",
            "snippet": "The US is allowing the purchase of Russian oil that’s stranded at sea after the war on Iran led to higher energy prices.",
            "isNew": true
          },
          {
            "title": "What is the strait of Hormuz and can the US stop Iran from blocking it?",
            "link": "https://www.theguardian.com/world/2026/mar/16/what-is-the-strait-of-hormuz-can-us-stop-iran-blocking-it",
            "source": "guardian",
            "sources": [
              "guardian"
            ],
            "pubDate": "Mon, 16 Mar 2026 12:56:25 GMT",
            "snippet": "Energy prices have soared as Iranian strikes and reports of mines prevent ships from transiting the chokepointMiddle East crisis – live updatesMore than 1,000 cargo ships, mainly oil and gas tankers, ",
            "isNew": true
          },
          {
            "title": "Iran hits key UAE oil port and Dubai airport",
            "link": "https://www.bbc.com/news/articles/crl4gxgkkylo?at_medium=RSS&at_campaign=rss",
            "source": "bbc",
            "sources": [
              "bbc"
            ],
            "pubDate": "Mon, 16 Mar 2026 12:43:32 GMT",
            "snippet": "The port of Fujairah plays a crucial role in helping keep global supplies moving when the Strait of Hormuz is blocked. ",
            "isNew": true
          }
        ]
      },
      {
        "category_id": "politics",
        "category_name": "국내 정치",
        "category_icon": "🏛️",
        "count": 11,
        "new_count": 11,
        "articles": [
          {
            "title": "Gulf states may be covertly encouraging attacks by US, Iran foreign minister says",
            "link": "https://www.theguardian.com/world/2026/mar/16/gulf-states-may-be-covertly-encouraging-attacks-by-us-irans-foreign-minister-says",
            "source": "guardian",
            "sources": [
              "guardian"
            ],
            "pubDate": "Mon, 16 Mar 2026 20:27:51 GMT",
            "snippet": "Abbas Araghchi demands clarification on reports Saudi crown prince urged Donald Trump to ‘hit the Iranians hard’Middle East crisis – live updatesSome Gulf states hosting US forces may be covertly enco",
            "isNew": true
          },
          {
            "title": "What Are Trump’s Positions on Iran? They Can Change by the Sentence.",
            "link": "https://www.nytimes.com/2026/03/16/us/politics/trump-iran-war.html",
            "source": "nytimes",
            "sources": [
              "nytimes"
            ],
            "pubDate": "Mon, 16 Mar 2026 20:14:51 +0000",
            "snippet": "The president is no stranger to staking out contradictory stands, part of what his aides say is his negotiating style. But on Iran, his shifting positions are colliding with the consequences of war.",
            "isNew": true
          },
          {
            "title": "European countries reject Trump’s call for help to reopen strait of Hormuz",
            "link": "https://www.theguardian.com/world/2026/mar/16/europe-donald-trump-strait-hormuz-iran",
            "source": "guardian",
            "sources": [
              "guardian"
            ],
            "pubDate": "Mon, 16 Mar 2026 19:30:43 GMT",
            "snippet": "Leaders seek a diplomatic solution despite US president’s threat of ‘a very bad future’ for Nato unless it provides warshipsMiddle East crisis – live updatesEuropean countries have ruled out sending w",
            "isNew": true
          },
          {
            "title": "After Trump’s Call to Send Warships to Strait of Hormuz, Nations Respond With Caution",
            "link": "https://www.nytimes.com/2026/03/15/world/middleeast/trump-strait-of-hormuz-iran-warships.html",
            "source": "nytimes",
            "sources": [
              "nytimes"
            ],
            "pubDate": "Mon, 16 Mar 2026 18:25:06 +0000",
            "snippet": "President Trump has urged China, Britain, France, Japan and South Korea to send warships to help reopen the waterway, even though they are not involved in the U.S.-Israeli attack on Iran.",
            "isNew": true
          },
          {
            "title": "Ben Jennings on Donald Trump’s plea for European support for his war on Iran – cartoon",
            "link": "https://www.theguardian.com/commentisfree/picture/2026/mar/16/ben-jennings-donald-trumps-plea-european-support-for-his-war-on-iran-cartoon",
            "source": "guardian",
            "sources": [
              "guardian"
            ],
            "pubDate": "Mon, 16 Mar 2026 17:45:50 GMT",
            "snippet": "Continue reading...",
            "isNew": true
          },
          {
            "title": "Trump’s Threat to Delay Summit With Xi Casts New Shadow Over China Relations",
            "link": "https://www.nytimes.com/2026/03/16/world/middleeast/trump-visit-xi-china-iran.html",
            "source": "nytimes",
            "sources": [
              "nytimes"
            ],
            "pubDate": "Mon, 16 Mar 2026 16:37:10 +0000",
            "snippet": "President Trump warned that he could postpone a meeting set to begin in just over two weeks if China refuses to help reopen the Strait of Hormuz.",
            "isNew": true
          },
          {
            "title": "US, Israel now know ‘what kind of nation they are dealing with’",
            "link": "https://www.aljazeera.com/video/newsfeed/2026/3/16/us-israel-now-know-what-kind-of-nation-they-are-dealing?traffic_source=rss",
            "source": "aljazeera",
            "sources": [
              "aljazeera"
            ],
            "pubDate": "Mon, 16 Mar 2026 16:00:08 +0000",
            "snippet": "Iran’s Foreign Minister Abbas Araghchi says his country has shown it is ready to take the war “as far as necessary&quot;.",
            "isNew": true
          },
          {
            "title": "Iran officials tout ‘Trump-burning’ celebration amid battle of narratives",
            "link": "https://www.aljazeera.com/news/2026/3/16/iran-officials-tout-trump-burning-celebration-amid-battle-of-narratives?traffic_source=rss",
            "source": "aljazeera",
            "sources": [
              "aljazeera"
            ],
            "pubDate": "Mon, 16 Mar 2026 14:55:53 +0000",
            "snippet": "Iranian state media calls for turning fire festival into a symbolic protest by burning figures of Trump and Netanyahu.",
            "isNew": true
          },
          {
            "title": "With Iran War, Trump Risks Stepping on Gains From His Own Tax Cuts",
            "link": "https://www.nytimes.com/2026/03/16/us/politics/trump-iran-tax-cuts.html",
            "source": "nytimes",
            "sources": [
              "nytimes"
            ],
            "pubDate": "Mon, 16 Mar 2026 14:53:29 +0000",
            "snippet": "President Trump’s war in Iran has raised some costs just as many Americans are starting to see savings from last year’s tax cuts.",
            "isNew": true
          },
          {
            "title": "Kenya and Russia agree no Kenyans will be recruited for Ukraine war",
            "link": "https://www.aljazeera.com/news/2026/3/16/kenya-and-russia-agree-no-kenyans-will-be-recruited-for-ukraine-war?traffic_source=rss",
            "source": "aljazeera",
            "sources": [
              "aljazeera"
            ],
            "pubDate": "Mon, 16 Mar 2026 14:14:34 +0000",
            "snippet": "Kenyan foreign minister meets Russian counterpart amid reports that hundreds of Kenyans are fighting in Russia, Ukraine.",
            "isNew": true
          }
        ]
      },
      {
        "category_id": "other",
        "category_name": "기타",
        "category_icon": "📰",
        "count": 5,
        "new_count": 5,
        "articles": [
          {
            "title": "Fifth Member of Iranian Soccer Team Reverses Decision on Asylum",
            "link": "https://www.nytimes.com/2026/03/16/world/middleeast/iran-soccer-team-asylum-australia.html",
            "source": "nytimes",
            "sources": [
              "nytimes"
            ],
            "pubDate": "Mon, 16 Mar 2026 18:41:26 +0000",
            "snippet": "Five of the seven members of the Iranian women’s national team who originally sought asylum in Australia after a tournament have changed their minds.",
            "isNew": true
          },
          {
            "title": "Quran echoes loudly as Palestinian reciters gather in Gaza",
            "link": "https://www.aljazeera.com/features/2026/3/16/quran-echoes-loudly-as-palestinian-reciters-gather-in-gaza?traffic_source=rss",
            "source": "aljazeera",
            "sources": [
              "aljazeera"
            ],
            "pubDate": "Mon, 16 Mar 2026 12:38:42 +0000",
            "snippet": "Quran memorisers in Gaza overcome devastation from war, reciting the holy book as a source of hope and strength.",
            "isNew": true
          },
          {
            "title": "A Timeline of the Tensions Between the Islamic Republic of Iran and the U.S.",
            "link": "https://www.nytimes.com/2026/03/15/world/middleeast/united-states-iran-history.html",
            "source": "nytimes",
            "sources": [
              "nytimes"
            ],
            "pubDate": "Mon, 16 Mar 2026 12:17:09 +0000",
            "snippet": "The governments of both countries have repeatedly cast the other as evil, perpetuating a cycle that has culminated in the present war.",
            "isNew": true
          },
          {
            "title": "Iran still playing in World Cup 2026 despite withdrawal rumours, AFC says",
            "link": "https://www.aljazeera.com/sports/2026/3/16/iran-still-playing-in-world-cup-2026-despite-withdrawal-rumours-afc-says?traffic_source=rss",
            "source": "aljazeera",
            "sources": [
              "aljazeera"
            ],
            "pubDate": "Mon, 16 Mar 2026 11:21:07 +0000",
            "snippet": "Asian Football Confederation says it hasn&#039;t received any notification of Iran pulling out of upcoming World Cup.",
            "isNew": true
          },
          {
            "title": "Who wants what from the Iran war?",
            "link": "https://www.bbc.com/news/articles/cgk2lm5znyro?at_medium=RSS&at_campaign=rss",
            "source": "bbc",
            "sources": [
              "bbc"
            ],
            "pubDate": "Mon, 16 Mar 2026 11:00:03 GMT",
            "snippet": "Most people, although not everybody, want this war to end as quickly as possible. But on what terms?",
            "isNew": true
          }
        ]
      },
      {
        "category_id": "regional",
        "category_name": "지역 정세",
        "category_icon": "🌍",
        "count": 4,
        "new_count": 4,
        "articles": [
          {
            "title": "서방 5개국 \"레바논서 이스라엘-헤즈볼라 적대행위 중단해야\"",
            "link": "https://www.yna.co.kr/view/AKR20260317007800072",
            "source": "yonhap",
            "sources": [
              "yonhap"
            ],
            "pubDate": "Tue, 17 Mar 2026 05:25:43 +0900",
            "snippet": "(뉴욕=연합뉴스) 이지헌 특파원 = 캐나다와 프랑스, 독일, 이탈리아, 영국 정상이 16일(현지시간) 레바논에서 이스라엘의 지상군 공세가 참혹한...",
            "isNew": true
          },
          {
            "title": "Israel’s Expanding Ground Assault in Lebanon Meets Resistance in Hilltop Town",
            "link": "https://www.nytimes.com/2026/03/16/world/middleeast/lebanon-strategic-town-khiam.html",
            "source": "nytimes",
            "sources": [
              "nytimes"
            ],
            "pubDate": "Mon, 16 Mar 2026 18:53:51 +0000",
            "snippet": "The town of Khiam’s location on high ground just a few miles north of the border between Israel and Lebanon has made it coveted territory over multiple conflicts.",
            "isNew": true
          },
          {
            "title": "Israeli Schools Begin Reopening in Some Areas Seen as Safer",
            "link": "https://www.nytimes.com/2026/03/16/world/middleeast/israel-schools.html",
            "source": "nytimes",
            "sources": [
              "nytimes"
            ],
            "pubDate": "Mon, 16 Mar 2026 18:02:40 +0000",
            "snippet": "Some classes resumed on Monday in areas far from the populous cities and border regions that have come under attack in the conflict with Iran and the Iran-backed militia, Hezbollah.",
            "isNew": true
          },
          {
            "title": "The US-Israeli strategy against Iran is working. Here is why",
            "link": "https://www.aljazeera.com/opinions/2026/3/16/the-us-israeli-strategy-against-iran-is-working-here-is-why?traffic_source=rss",
            "source": "aljazeera",
            "sources": [
              "aljazeera"
            ],
            "pubDate": "Mon, 16 Mar 2026 13:39:55 +0000",
            "snippet": "Every aspect of Iran’s ability to project regional power is being successfully degraded.",
            "isNew": true
          }
        ]
      },
      {
        "category_id": "humanitarian",
        "category_name": "인도주의/피해",
        "category_icon": "🏥",
        "count": 3,
        "new_count": 3,
        "articles": [
          {
            "title": "Trump’s threats to Nato reveal glaring absence of any strategy on Iran",
            "link": "https://www.theguardian.com/world/2026/mar/16/donald-trump-nato-threats-glaring-absence-iran-strategy",
            "source": "guardian",
            "sources": [
              "guardian"
            ],
            "pubDate": "Mon, 16 Mar 2026 18:04:01 GMT",
            "snippet": "White House seems to have failed to anticipate that Tehran would fight back by trying to impose costs on the westMiddle East crisis – live updatesIf there was a moment when the absence of a US strateg",
            "isNew": true
          },
          {
            "title": "'My mother cried out one last time': Palestinian boy, 12, describes how Israeli forces killed his family in car",
            "link": "https://www.bbc.com/news/articles/c70n2x7p22do?at_medium=RSS&at_campaign=rss",
            "source": "bbc",
            "sources": [
              "bbc",
              "nytimes"
            ],
            "pubDate": "Mon, 16 Mar 2026 17:57:45 GMT",
            "snippet": "Khaled Bani Odeh's parents and two brothers were shot dead as they drove home from a shopping trip in the occupied West Bank.",
            "isNew": true
          },
          {
            "title": "Civilians pulled from rubble after US-Israeli strikes on Tehran",
            "link": "https://www.aljazeera.com/video/newsfeed/2026/3/16/civilians-pulled-from-rubble-after-us-israeli-strikes-on-tehran?traffic_source=rss",
            "source": "aljazeera",
            "sources": [
              "aljazeera"
            ],
            "pubDate": "Mon, 16 Mar 2026 17:27:54 +0000",
            "snippet": "Rescuers have pulled civilians from the rubble after a new wave of US-Israeli strikes targeted Tehran. ",
            "isNew": true
          }
        ]
      },
      {
        "category_id": "diplomacy",
        "category_name": "외교/협상",
        "category_icon": "🤝",
        "count": 1,
        "new_count": 1,
        "articles": [
          {
            "title": "In Lebanon, Israel is using occupation as negotiating tool, say analysts",
            "link": "https://www.aljazeera.com/features/2026/3/16/in-lebanon-israel-is-using-occupation-as-negotiating-tool-say-analysts?traffic_source=rss",
            "source": "aljazeera",
            "sources": [
              "aljazeera"
            ],
            "pubDate": "Mon, 16 Mar 2026 12:05:03 +0000",
            "snippet": "Israel is using military occupation of southern Lebanon and displacement crisis to dictate ceasefire terms, say experts.",
            "isNew": true
          }
        ]
      }
    ],
    "recent_30min": {
      "total_new": 50,
      "by_category": {
        "economy": {
          "count": 13,
          "titles": [
            {
              "title": "Middle East crisis live: Trump vents frustration with allies as European countries resist demand for help in strait of Hormuz",
              "link": "https://www.theguardian.com/world/live/2026/mar/16/iran-war-live-updates-news-oil-trump-hormuz-dubai-airport-israel-targets",
              "source": "guardian"
            },
            {
              "title": "Starmer distances UK from Iran war as EU leaders rule out sending warships",
              "link": "https://www.theguardian.com/world/2026/mar/16/starmer-distances-uk-from-iran-war-as-eu-leaders-rule-out-sending-warships",
              "source": "guardian"
            },
            {
              "title": "Trump says Hormuz Strait help ‘on the way’ as allies reject military action",
              "link": "https://www.aljazeera.com/news/2026/3/16/trump-says-hormuz-strait-help-on-the-way-as-allies-reject-military-action?traffic_source=rss",
              "source": "aljazeera"
            },
            {
              "title": "Sri Lanka brings in four-day week to eke out stocks of oil and gas hit by Iran war",
              "link": "https://www.theguardian.com/world/2026/mar/16/sri-lanka-four-day-week-oil-and-gas-iran-war",
              "source": "guardian"
            },
            {
              "title": "IEA to consider release of more oil reserves as Iran war keeps prices high",
              "link": "https://www.theguardian.com/business/2026/mar/16/iea-release-oil-reserves-iran-war-prices-strait-of-hormuz",
              "source": "guardian"
            }
          ]
        },
        "politics": {
          "count": 11,
          "titles": [
            {
              "title": "Gulf states may be covertly encouraging attacks by US, Iran foreign minister says",
              "link": "https://www.theguardian.com/world/2026/mar/16/gulf-states-may-be-covertly-encouraging-attacks-by-us-irans-foreign-minister-says",
              "source": "guardian"
            },
            {
              "title": "What Are Trump’s Positions on Iran? They Can Change by the Sentence.",
              "link": "https://www.nytimes.com/2026/03/16/us/politics/trump-iran-war.html",
              "source": "nytimes"
            },
            {
              "title": "European countries reject Trump’s call for help to reopen strait of Hormuz",
              "link": "https://www.theguardian.com/world/2026/mar/16/europe-donald-trump-strait-hormuz-iran",
              "source": "guardian"
            },
            {
              "title": "After Trump’s Call to Send Warships to Strait of Hormuz, Nations Respond With Caution",
              "link": "https://www.nytimes.com/2026/03/15/world/middleeast/trump-strait-of-hormuz-iran-warships.html",
              "source": "nytimes"
            },
            {
              "title": "Ben Jennings on Donald Trump’s plea for European support for his war on Iran – cartoon",
              "link": "https://www.theguardian.com/commentisfree/picture/2026/mar/16/ben-jennings-donald-trumps-plea-european-support-for-his-war-on-iran-cartoon",
              "source": "guardian"
            }
          ]
        },
        "military": {
          "count": 12,
          "titles": [
            {
              "title": "Hezbollah rocket hits a residential building in Israel’s Nahariya",
              "link": "https://www.aljazeera.com/video/newsfeed/2026/3/16/hezbollah-rocket-hits-a-residential-building-in-israels-nahariya?traffic_source=rss",
              "source": "aljazeera"
            },
            {
              "title": "Israeli forces in southern Lebanon as ground operation announced",
              "link": "https://www.aljazeera.com/video/newsfeed/2026/3/16/israeli-forces-in-southern-lebanon-as-ground-operation-announced?traffic_source=rss",
              "source": "aljazeera"
            },
            {
              "title": "The Guardian view on Trump’s war with Iran: if the US is winning, why ask Nato for help? | Editorial",
              "link": "https://www.theguardian.com/commentisfree/2026/mar/16/the-guardian-view-on-trumps-war-with-iran-if-the-us-is-winning-why-ask-nato-for-help",
              "source": "guardian"
            },
            {
              "title": "In Choosing ‘Epic Fury,’ Trump Names a War and Defines His Presidency",
              "link": "https://www.nytimes.com/2026/03/16/us/politics/trump-operation-epic-fury-anger.html",
              "source": "nytimes"
            },
            {
              "title": "Israel’s plan to expand Lebanon ground campaign fuels fears of prolonged occupation",
              "link": "https://www.theguardian.com/world/2026/mar/16/israel-expansion-lebanon-ground-campaign-fears-prolonged-occupation",
              "source": "guardian"
            }
          ]
        },
        "regional": {
          "count": 4,
          "titles": [
            {
              "title": "서방 5개국 \"레바논서 이스라엘-헤즈볼라 적대행위 중단해야\"",
              "link": "https://www.yna.co.kr/view/AKR20260317007800072",
              "source": "yonhap"
            },
            {
              "title": "Israel’s Expanding Ground Assault in Lebanon Meets Resistance in Hilltop Town",
              "link": "https://www.nytimes.com/2026/03/16/world/middleeast/lebanon-strategic-town-khiam.html",
              "source": "nytimes"
            },
            {
              "title": "Israeli Schools Begin Reopening in Some Areas Seen as Safer",
              "link": "https://www.nytimes.com/2026/03/16/world/middleeast/israel-schools.html",
              "source": "nytimes"
            },
            {
              "title": "The US-Israeli strategy against Iran is working. Here is why",
              "link": "https://www.aljazeera.com/opinions/2026/3/16/the-us-israeli-strategy-against-iran-is-working-here-is-why?traffic_source=rss",
              "source": "aljazeera"
            }
          ]
        },
        "other": {
          "count": 5,
          "titles": [
            {
              "title": "Fifth Member of Iranian Soccer Team Reverses Decision on Asylum",
              "link": "https://www.nytimes.com/2026/03/16/world/middleeast/iran-soccer-team-asylum-australia.html",
              "source": "nytimes"
            },
            {
              "title": "Quran echoes loudly as Palestinian reciters gather in Gaza",
              "link": "https://www.aljazeera.com/features/2026/3/16/quran-echoes-loudly-as-palestinian-reciters-gather-in-gaza?traffic_source=rss",
              "source": "aljazeera"
            },
            {
              "title": "A Timeline of the Tensions Between the Islamic Republic of Iran and the U.S.",
              "link": "https://www.nytimes.com/2026/03/15/world/middleeast/united-states-iran-history.html",
              "source": "nytimes"
            },
            {
              "title": "Iran still playing in World Cup 2026 despite withdrawal rumours, AFC says",
              "link": "https://www.aljazeera.com/sports/2026/3/16/iran-still-playing-in-world-cup-2026-despite-withdrawal-rumours-afc-says?traffic_source=rss",
              "source": "aljazeera"
            },
            {
              "title": "Who wants what from the Iran war?",
              "link": "https://www.bbc.com/news/articles/cgk2lm5znyro?at_medium=RSS&at_campaign=rss",
              "source": "bbc"
            }
          ]
        },
        "humanitarian": {
          "count": 4,
          "titles": [
            {
              "title": "Trump’s threats to Nato reveal glaring absence of any strategy on Iran",
              "link": "https://www.theguardian.com/world/2026/mar/16/donald-trump-nato-threats-glaring-absence-iran-strategy",
              "source": "guardian"
            },
            {
              "title": "'My mother cried out one last time': Palestinian boy, 12, describes how Israeli forces killed his family in car",
              "link": "https://www.bbc.com/news/articles/c70n2x7p22do?at_medium=RSS&at_campaign=rss",
              "source": "bbc"
            },
            {
              "title": "Civilians pulled from rubble after US-Israeli strikes on Tehran",
              "link": "https://www.aljazeera.com/video/newsfeed/2026/3/16/civilians-pulled-from-rubble-after-us-israeli-strikes-on-tehran?traffic_source=rss",
              "source": "aljazeera"
            },
            {
              "title": "4 Palestinians Killed When Israeli Forces Open Fire on West Bank Family",
              "link": "https://www.nytimes.com/2026/03/15/world/middleeast/palestinian-family-killed-west-bank.html",
              "source": "nytimes"
            }
          ]
        },
        "diplomacy": {
          "count": 1,
          "titles": [
            {
              "title": "In Lebanon, Israel is using occupation as negotiating tool, say analysts",
              "link": "https://www.aljazeera.com/features/2026/3/16/in-lebanon-israel-is-using-occupation-as-negotiating-tool-say-analysts?traffic_source=rss",
              "source": "aljazeera"
            }
          ]
        }
      }
    }
  },
  "historical_comparison": [
    {
      "name": "걸프전 (1991)",
      "duration_days": 42,
      "type": "공습→지상전",
      "involved_countries": 35,
      "ended_by": "군사적 패배"
    },
    {
      "name": "이라크전 주요전투 (2003)",
      "duration_days": 42,
      "type": "침공",
      "involved_countries": 4,
      "ended_by": "정권 교체"
    },
    {
      "name": "2006 레바논 전쟁",
      "duration_days": 34,
      "type": "공습+지상전",
      "involved_countries": 2,
      "ended_by": "UN 휴전"
    },
    {
      "name": "2008 가자 전쟁",
      "duration_days": 22,
      "type": "공습→지상전",
      "involved_countries": 2,
      "ended_by": "일방적 휴전"
    },
    {
      "name": "2014 가자 전쟁",
      "duration_days": 50,
      "type": "공습+지상전",
      "involved_countries": 2,
      "ended_by": "협상 휴전"
    },
    {
      "name": "리비아 NATO 개입 (2011)",
      "duration_days": 222,
      "type": "공습 작전",
      "involved_countries": 18,
      "ended_by": "정권 교체"
    },
    {
      "name": "포클랜드 전쟁 (1982)",
      "duration_days": 74,
      "type": "해·공·지상전",
      "involved_countries": 2,
      "ended_by": "군사적 패배"
    },
    {
      "name": "코소보 NATO 폭격 (1999)",
      "duration_days": 78,
      "type": "공습 작전",
      "involved_countries": 19,
      "ended_by": "항복"
    },
    {
      "name": "이스라엘-하마스 (2023-25)",
      "duration_days": 470,
      "type": "공습+지상전",
      "involved_countries": 2,
      "ended_by": "협상 휴전"
    },
    {
      "name": "이란-이라크 전쟁 (1980-88)",
      "duration_days": 2922,
      "type": "총력전",
      "involved_countries": 2,
      "ended_by": "UN 휴전"
    },
    {
      "name": "러시아-우크라이나 전쟁 (2022-)",
      "duration_days": 1105,
      "type": "전면 침공+소모전",
      "involved_countries": 2,
      "ended_by": "진행 중"
    },
    {
      "name": "2025 이란-이스라엘 교전",
      "duration_days": 12,
      "type": "공습 작전",
      "involved_countries": 3,
      "ended_by": "중재 휴전"
    }
  ],
  "economic_indicators": {
    "VIX": {
      "price": 23.51,
      "change": -3.68,
      "changePercent": -13.53,
      "prev": 27.19
    },
    "WTI": {
      "price": 93.75,
      "change": -4.96,
      "changePercent": -5.02,
      "prev": 98.71
    },
    "US10Y": {
      "price": 4.22,
      "change": -0.06,
      "changePercent": -1.4,
      "prev": 4.28
    },
    "GOLD": {
      "price": 5022.1,
      "change": -30.4,
      "changePercent": -0.6,
      "prev": 5052.5
    },
    "US2Y": {
      "price": 3.6,
      "change": 0,
      "changePercent": 0,
      "prev": 3.6
    },
    "BRENT": {
      "price": 100.3,
      "change": -2.84,
      "changePercent": -2.75,
      "prev": 103.14
    },
    "DXY": {
      "price": 100.5,
      "change": 0.76,
      "changePercent": 0.76,
      "prev": 99.74
    }
  },
  "critical_events": [
    {
      "id": "capital_attack",
      "name": "수도 직접 공격/포위",
      "severity": "high",
      "confidence": 1,
      "matchCount": 4,
      "direction": "shorten"
    },
    {
      "id": "conflict_expansion",
      "name": "전선 확대/신규 참전국",
      "severity": "moderate",
      "confidence": 0.6666666666666666,
      "matchCount": 2,
      "direction": "lengthen"
    }
  ],
  "feeds_loaded": 7,
  "feeds_total": 8
}