{
  "timestamp": "2026-03-12T04:11:45.523Z",
  "war_day": 12,
  "probabilities": {
    "1개월 내 (~3월)": 20,
    "2~3개월 (4~5월)": 40.2,
    "4~6개월 (6~8월)": 23.9,
    "7~12개월 (9월~27/2월)": 12.1,
    "1년 초과": 3.8
  },
  "factors": [
    {
      "factor": "트럼프 대통령 4-5주 예상 발언",
      "impact": "2~3개월 내 종전 확률 상승",
      "weight": "+8%p (2~3개월) (잔존44%)",
      "direction": "shorten",
      "detail": "트럼프 대통령이 공개적으로 전쟁이 \"4-5주 내\"에 끝날 것이라고 발언했습니다.",
      "keywords": [
        "trump",
        "4 week",
        "5 week",
        "timeline",
        "end war"
      ],
      "applied": "2026-03-01",
      "active": true,
      "decay": 0.4413
    },
    {
      "factor": "이스라엘 제공권 장악 (이란 방공 80% 파괴)",
      "impact": "단기 종전 가능성 증가",
      "weight": "+4%p (1개월내), +6%p (2~3개월) (잔존78%)",
      "direction": "shorten",
      "detail": "이스라엘이 이란 방공망의 핵심을 무력화했습니다.",
      "keywords": [
        "air superi",
        "air defens",
        "s-300",
        "s-400",
        "radar",
        "anti-air"
      ],
      "applied": "2026-03-01",
      "active": true,
      "decay": 0.7765
    },
    {
      "factor": "확전 뉴스 우세 (확전8:휴전2)",
      "impact": "전쟁 장기화 가능성 (확전비율 80%)",
      "weight": "+0.03%p (4~6개월)",
      "direction": "lengthen",
      "detail": "언론에서 휴전보다 확전을 더 많이 보도하고 있습니다.",
      "keywords": [
        "escalat",
        "intensif",
        "expand",
        "widen"
      ],
      "applied": "실시간",
      "active": true,
      "decay": 1
    },
    {
      "factor": "호르무즈 해협 봉쇄 → 국제 경제 압력",
      "impact": "경제적 압력으로 빠른 해결 촉구",
      "weight": "+3%p (1개월내), +5%p (2~3개월) (잔존78%)",
      "direction": "shorten",
      "detail": "세계 원유의 약 20%가 호르무즈 해협을 통과합니다.",
      "keywords": [
        "hormuz",
        "strait",
        "oil price",
        "blockade",
        "shipping",
        "tanker"
      ],
      "applied": "2026-03-01",
      "active": true,
      "decay": 0.7765
    },
    {
      "factor": "9개국 참전 - 분쟁 복잡성 증가",
      "impact": "다자간 분쟁으로 협상 복잡화",
      "weight": "+5%p (4~6개월), +3%p (7~12개월) (잔존49%)",
      "direction": "lengthen",
      "detail": "참전국이 많을수록 휴전 협상이 복잡해집니다.",
      "keywords": [
        "coalition",
        "allies",
        "nato",
        "joint operation",
        "multinational"
      ],
      "applied": "2026-03-02",
      "active": true,
      "decay": 0.4913
    },
    {
      "factor": "하메네이 사망 - 이란 지도부 공백",
      "impact": "정권 붕괴 가능성과 내부 혼란 장기화 위험",
      "weight": "+4%p (2~3개월), +4%p (4~6개월) (잔존54%)",
      "direction": "mixed",
      "detail": "최고지도자의 사망으로 정권 내부에 큰 혼란이 발생합니다.",
      "keywords": [
        "khamenei",
        "supreme leader",
        "succession",
        "leadership",
        "regime"
      ],
      "applied": "2026-03-03",
      "active": true,
      "decay": 0.5413
    },
    {
      "factor": "쿠르드족 지상군 이란 국경 진입",
      "impact": "지상전 확대로 전쟁 장기화 위험",
      "weight": "+4%p (4~6개월), +3%p (7~12개월) (잔존59%)",
      "direction": "lengthen",
      "detail": "쿠르드 페쉬메르가 부대가 북부 전선을 열었습니다.",
      "keywords": [
        "kurd",
        "peshmerga",
        "ground",
        "border",
        "northern front"
      ],
      "applied": "2026-03-04",
      "active": true,
      "decay": 0.5913
    },
    {
      "factor": "이란 3/5 CIA 통한 협상 시도",
      "impact": "이란의 협상 의지 → 단기 종전 가능성 증가",
      "weight": "+5%p (1개월내), +8%p (2~3개월) (잔존64%)",
      "direction": "shorten",
      "detail": "이란이 비밀 채널을 통해 협상을 시도했습니다.",
      "keywords": [
        "cia",
        "backchannel",
        "secret talk",
        "negotiat",
        "iran offer",
        "surrender"
      ],
      "applied": "2026-03-05",
      "active": true,
      "decay": 0.6413
    },
    {
      "factor": "걸프전(42일) 패턴 유사성",
      "impact": "제공권→지상작전→빠른 종결 패턴",
      "weight": "참고: 걸프전 42일, 코소보 78일, 포클랜드 74일",
      "direction": "reference",
      "detail": "이번 전쟁은 걸프전과 매우 유사한 패턴을 보입니다.",
      "keywords": [
        "gulf war",
        "desert storm",
        "pattern",
        "historical"
      ],
      "applied": "2026-02-28",
      "active": true,
      "decay": 1
    },
    {
      "factor": "협상/외교 뉴스 2건 감지",
      "impact": "외교 움직임 미약",
      "weight": "+0.00%p (1개월내), +0.00%p (2~3개월)",
      "direction": "shorten",
      "detail": "실시간 뉴스에서 협상 관련 기사 2건이 감지되었습니다.",
      "keywords": [
        "negotiat",
        "talks",
        "dialog",
        "diplomat",
        "mediati"
      ],
      "applied": "실시간",
      "active": true,
      "decay": 1
    },
    {
      "factor": "지역 확산 뉴스 28건 감지",
      "impact": "주변국 대규모 연루 → 장기화 위험 높음",
      "weight": "+0.03%p (4~6개월), +0.03%p (7~12개월)",
      "direction": "lengthen",
      "detail": "주변국을 언급하는 기사 28건이 감지되었습니다.",
      "keywords": [
        "saudi",
        "uae",
        "qatar",
        "iraq",
        "lebanon",
        "turkey"
      ],
      "applied": "실시간",
      "active": true,
      "decay": 1
    },
    {
      "factor": "미 상원 전쟁 결의안 부결",
      "impact": "미국 내 정치적 지지로 군사작전 지속 가능",
      "weight": "+3%p (2~3개월), +2%p (4~6개월) (잔존59%)",
      "direction": "mixed",
      "detail": "미 상원이 전쟁권한 제한 결의안을 부결시켰습니다.",
      "keywords": [
        "senate",
        "resolution",
        "war powers",
        "congress",
        "vote"
      ],
      "applied": "2026-03-04",
      "active": true,
      "decay": 0.5913
    },
    {
      "factor": "사우디/UAE 연합군 참전",
      "impact": "이란 포위망 강화 → 조기 항복 가능성",
      "weight": "+3%p (1개월내), +5%p (2~3개월) (잔존54%)",
      "direction": "shorten",
      "detail": "사우디와 UAE가 연합군에 합류했습니다.",
      "keywords": [
        "saudi",
        "uae",
        "coalition",
        "join",
        "alliance",
        "gcc"
      ],
      "applied": "2026-03-03",
      "active": true,
      "decay": 0.5413
    },
    {
      "factor": "[중대 이벤트] 일방적 전투 축소/자제 선언",
      "impact": "교전국의 일방적 전투 축소 또는 자제 선언. 역사적으로 패전국의 자발적 전선 축소는 80% 이상 공식 항복의 전조.",
      "weight": "+3.3%p (1개월내), +4.7%p (2~3개월), -2.0%p (4~6개월), -2.0%p (7~12개월), -0.7%p (1년초과)",
      "direction": "shorten",
      "detail": "교전국의 일방적 전투 축소 또는 자제 선언. 역사적으로 패전국의 자발적 전선 축소는 80% 이상 공식 항복의 전조.\n\n신뢰도: 높음 (67%), 관련 기사 2건 감지.\n관련: UN Security Council adopts Gulf countries’ draft resolution",
      "keywords": [
        "halt",
        "attack",
        "stop",
        "attack",
        "neighb",
        "no more",
        "attack",
        "withdraw",
        "forces",
        "pull back",
        "troops",
        "unilateral",
        "ceasefire",
        "reduce",
        "operation",
        "de-escalat",
        "announc",
        "restrain",
        "attack",
        "not attack",
        "suspend",
        "operation"
      ],
      "applied": "2026-03-12",
      "active": true,
      "severity": "high"
    },
    {
      "factor": "[중대 이벤트] 수도 직접 공격/포위",
      "impact": "수도 직접 공격. 베오그라드(1999): 78일 폭격 후 항복. 바그다드(2003): 21일만에 함락. 수도 타격은 전쟁 지속 의지를 급격히 약화.",
      "weight": "+4.0%p (1개월내), +6.0%p (2~3개월), -2.0%p (4~6개월), -2.0%p (7~12개월), -1.0%p (1년초과)",
      "direction": "shorten",
      "detail": "수도 직접 공격. 베오그라드(1999): 78일 폭격 후 항복. 바그다드(2003): 21일만에 함락. 수도 타격은 전쟁 지속 의지를 급격히 약화.\n\n신뢰도: 확실 (100%), 관련 기사 4건 감지.\n관련: Israel Bombards Lebanese Capital in Latest Round of Strikes | Iran holds a public mourning ceremony for commanders killed by strikes.",
      "keywords": [
        "capital",
        "bomb",
        "capital",
        "strike",
        "capital",
        "attack",
        "capital",
        "siege",
        "capital",
        "pound",
        "capital",
        "explosion",
        "tehran",
        "bomb",
        "tehran",
        "strike",
        "tehran",
        "pound",
        "tehran",
        "explosion"
      ],
      "applied": "2026-03-12",
      "active": true,
      "severity": "high"
    },
    {
      "factor": "[중대 이벤트] 전선 확대/신규 참전국",
      "impact": "분쟁 확대 또는 신규 참전. 역사적으로 참전국 1개 추가 시 평균 전쟁 기간 30~50% 증가 (Correlates of War 데이터).",
      "weight": "-1.3%p (1개월내), -2.0%p (2~3개월), +2.7%p (4~6개월), +2.0%p (7~12개월), +1.3%p (1년초과)",
      "direction": "lengthen",
      "detail": "분쟁 확대 또는 신규 참전. 역사적으로 참전국 1개 추가 시 평균 전쟁 기간 30~50% 증가 (Correlates of War 데이터).\n\n신뢰도: 높음 (67%), 관련 기사 2건 감지.\n관련: Israel bombards Beirut suburbs and southern Lebanon as conflict with Hezbollah escalates",
      "keywords": [
        "new front",
        "war spread",
        "conflict expand",
        "join",
        "war",
        "enter",
        "war",
        "open",
        "front",
        "declare war",
        "widen",
        "conflict",
        "second front",
        "new theater"
      ],
      "applied": "2026-03-12",
      "active": true,
      "severity": "moderate"
    },
    {
      "factor": "유가 급등 (WTI $94.45/배럴)",
      "impact": "중간 수준 경제 압력",
      "weight": "+2%p (1-2개월)",
      "direction": "shorten",
      "detail": "WTI 유가가 $94.45/배럴로 90달러 이상입니다. 호르무즈 해협 봉쇄와 맞물려 글로벌 에너지 시장에 큰 충격을 주고 있으며, 주요국들의 조기 종전 압력이 강화되고 있습니다.",
      "keywords": [
        "oil",
        "crude",
        "wti",
        "brent",
        "energy",
        "gas price"
      ],
      "applied": "실시간",
      "active": true
    },
    {
      "factor": "금값 사상최고 ($5155.6/oz)",
      "impact": "안전자산 수요 폭증 → 글로벌 불안 심화",
      "weight": "+2%p (4-6개월)",
      "direction": "lengthen",
      "detail": "금 가격이 온스당 $5155.6로 사상 최고 수준입니다. 투자자들이 안전자산으로 대거 이동하고 있으며, 이는 전쟁 장기화에 대한 시장의 우려를 반영합니다.",
      "keywords": [
        "gold",
        "safe haven",
        "precious metal",
        "investor"
      ],
      "applied": "실시간",
      "active": true
    }
  ],
  "news_signals": {
    "ceasefire_mentions": 2,
    "escalation_mentions": 8,
    "negotiation_mentions": 2,
    "casualty_mentions": 24.2,
    "peace_mentions": 2,
    "regional_spread": 28,
    "total_articles": 50,
    "new_articles": 50,
    "unique_events": 48,
    "duplicates_removed": 2
  },
  "latest_news": [
    {
      "title": "Middle East crisis live: Iraqi tankers hit as Iran targets oil supplies; US orders petroleum reserve release in bid to calm markets",
      "link": "https://www.theguardian.com/world/live/2026/mar/11/iran-war-live-updates-trump-oil-hormuz-protestors-us-israel-beirut-middle-east-latest-news",
      "pubDate": "Thu, 12 Mar 2026 04:04:57 GMT",
      "source": "guardian",
      "snippet": "Iraq officials say at least one person was killed in the attack on the tankers; US to release 172m barrels of oil from strategic reserveIran escalates attacks on infrastructure and transport across th",
      "isNew": true,
      "_sourceCount": 1,
      "_isDuplicated": false,
      "_clusterSize": 1,
      "_isDuplicate": false
    },
    {
      "title": "Fire erupts at Gaza camp after Israeli attack hits tents",
      "link": "https://www.aljazeera.com/video/newsfeed/2026/3/12/fire-erupts-at-gaza-camp-after-israeli-attack-hits-tents?traffic_source=rss",
      "pubDate": "Thu, 12 Mar 2026 03:25:41 +0000",
      "source": "aljazeera",
      "snippet": "Fire broke out at tents sheltering displaced Palestinians in Gaza’s Al-Ansar refugee camp after an Israeli strike.",
      "isNew": true,
      "_sourceCount": 1,
      "_isDuplicated": false,
      "_clusterSize": 1,
      "_isDuplicate": false
    },
    {
      "title": "Fuel tank fire rages in Bahrain after Iranian attack",
      "link": "https://www.aljazeera.com/video/newsfeed/2026/3/12/fuel-tank-fire-rages-in-bahrain-after-iranian-attack?traffic_source=rss",
      "pubDate": "Thu, 12 Mar 2026 03:15:15 +0000",
      "source": "aljazeera",
      "snippet": "Bahrain&#039;s interior ministry released footage of a massive blaze at a fuel storage facility following an Iranian attack.",
      "isNew": true,
      "_sourceCount": 1,
      "_isDuplicated": false,
      "_clusterSize": 1,
      "_isDuplicate": false
    },
    {
      "title": "Countries Scramble to Shore Up Global Oil Supplies as Ships Are Attacked",
      "link": "https://www.nytimes.com/2026/03/11/world/middleeast/oil-ships-lebanon-iran-israel.html",
      "pubDate": "Thu, 12 Mar 2026 02:52:17 +0000",
      "source": "nytimes",
      "snippet": "The United States and Israel launched more strikes against Iran, where crowds mourned military commanders killed in the war. Israel also bombed targets in Lebanon, where the death toll climbed.",
      "isNew": true,
      "_sourceCount": 1,
      "_isDuplicated": false,
      "_clusterSize": 1,
      "_isDuplicate": false
    },
    {
      "title": "UN Security Council adopts resolution condemning Iran’s attacks in the Gulf",
      "link": "https://www.aljazeera.com/news/2026/3/12/un-security-council-adopts-resolution-condemning-irans-attacks-in-the-gulf?traffic_source=rss",
      "pubDate": "Thu, 12 Mar 2026 02:44:48 +0000",
      "source": "aljazeera",
      "snippet": "UN Security Council draft resolution demanding Iran end its attacks on Gulf nations was cosponsored by 135 countries.",
      "isNew": true,
      "_isDuplicate": true,
      "_sourceCount": 1
    },
    {
      "title": "Who bombed the Iranian girls’ school, killing more than 170? What we know",
      "link": "https://www.aljazeera.com/news/2026/3/12/who-bombed-the-iranian-girls-school-killing-more-than-170-what-we-know?traffic_source=rss",
      "pubDate": "Thu, 12 Mar 2026 02:21:15 +0000",
      "source": "aljazeera",
      "snippet": "The attack on Shajareh Tayyebeh Elementary School quickly became a focal point of concern over civilian casualties.",
      "isNew": true,
      "_sourceCount": 1,
      "_isDuplicated": false,
      "_clusterSize": 1,
      "_isDuplicate": false
    },
    {
      "title": "U.S. to Release 172 Million Barrels of Oil From Strategic Reserves, Energy Dept. Says",
      "link": "https://www.nytimes.com/2026/03/11/world/middleeast/us-oil-reserves-trump-iran.html",
      "pubDate": "Thu, 12 Mar 2026 02:06:39 +0000",
      "source": "nytimes",
      "snippet": "The move aims to prevent prices from rising further because of the war in the Middle East.",
      "isNew": true,
      "_sourceCount": 1,
      "_isDuplicated": false,
      "_clusterSize": 1,
      "_isDuplicate": false
    },
    {
      "title": "Israeli strike hits Beirut waterfront near tents of displaced",
      "link": "https://www.aljazeera.com/video/newsfeed/2026/3/12/israeli-strike-hits-beirut-waterfront-near-tents-of-displaced?traffic_source=rss",
      "pubDate": "Thu, 12 Mar 2026 01:53:23 +0000",
      "source": "aljazeera",
      "snippet": "At least six people are dead from an Israeli strike on Beirut’s Ramlet al-Baida seafront.",
      "isNew": true,
      "_sourceCount": 1,
      "_isDuplicated": false,
      "_clusterSize": 1,
      "_isDuplicate": false
    },
    {
      "title": "U.S. at Fault in Strike on School in Iran, Preliminary Inquiry Says",
      "link": "https://www.nytimes.com/2026/03/11/us/politics/iran-school-missile-strike.html",
      "pubDate": "Thu, 12 Mar 2026 01:50:56 +0000",
      "source": "nytimes",
      "snippet": "Outdated targeting data may have resulted in a mistaken missile strike, according to the ongoing military investigation, which undercuts President Trump’s assertion that Iran could be to blame.",
      "isNew": true,
      "_isDuplicate": true,
      "_sourceCount": 1
    },
    {
      "title": "Iran’s authorities warn against protests as Israel threatens Basij forces",
      "link": "https://www.aljazeera.com/news/2026/3/12/irans-authorities-warn-against-protests-as-israel-threatens-basij-forces?traffic_source=rss",
      "pubDate": "Thu, 12 Mar 2026 01:35:06 +0000",
      "source": "aljazeera",
      "snippet": "Police chief says protesters seen as acting at the behest of the US and Israel will be treated as enemies. ",
      "isNew": true,
      "_sourceCount": 1,
      "_isDuplicated": false,
      "_clusterSize": 1,
      "_isDuplicate": false
    },
    {
      "title": "U.N. Security Council Condemns Iran’s Retaliatory Strikes in the Middle East",
      "link": "https://www.nytimes.com/2026/03/11/world/middleeast/un-security-council-condemns-iran-strikes.html",
      "pubDate": "Thu, 12 Mar 2026 01:32:08 +0000",
      "source": "nytimes",
      "snippet": "In an overwhelming vote, the council backed a resolution condemning Iran. A Russian proposal calling for an end to the war that didn’t assign blame or even name the parties, was rejected.",
      "isNew": true,
      "_sourceCount": 2,
      "_isDuplicated": true,
      "_clusterSize": 2,
      "_isDuplicate": false
    },
    {
      "title": "Israel Bombards Lebanese Capital in Latest Round of Strikes",
      "link": "https://www.nytimes.com/2026/03/11/world/middleeast/beirut-lebanon-israel-strikes.html",
      "pubDate": "Thu, 12 Mar 2026 00:48:59 +0000",
      "source": "nytimes",
      "snippet": "Lebanon’s health ministry said at least seven people were killed in the Beirut attacks early Thursday.",
      "isNew": true,
      "_sourceCount": 1,
      "_isDuplicated": false,
      "_clusterSize": 1,
      "_isDuplicate": false
    },
    {
      "title": "Qatar PM urges resilience and unity amid Iran strikes",
      "link": "https://www.aljazeera.com/video/newsfeed/2026/3/12/qatar-pm-urges-resilience-and-unity-amid-iran-strikes?traffic_source=rss",
      "pubDate": "Thu, 12 Mar 2026 00:35:43 +0000",
      "source": "aljazeera",
      "snippet": "Qatar’s Prime Minister calls for strengthening the country’s ability to withstand “hardship” amid regional war.",
      "isNew": true,
      "_sourceCount": 1,
      "_isDuplicated": false,
      "_clusterSize": 1,
      "_isDuplicate": false
    },
    {
      "title": "Israel bombards Beirut suburbs and southern Lebanon as conflict with Hezbollah escalates",
      "link": "https://www.theguardian.com/world/2026/mar/12/israel-bombards-beirut-southern-lebanon-hezbollah",
      "pubDate": "Thu, 12 Mar 2026 00:10:20 GMT",
      "source": "guardian",
      "snippet": "Hezbollah and Iran had launched joint attack on more than 50 targets including Israeli military basesMiddle East live – latest updatesIsraeli warplanes bombarded Beirut’s southern suburbs and southern",
      "isNew": true,
      "_sourceCount": 1,
      "_isDuplicated": false,
      "_clusterSize": 1,
      "_isDuplicate": false
    },
    {
      "title": "Eight Arab, Islamic countries condemn Israeli closure of Al-Aqsa Mosque",
      "link": "https://www.aljazeera.com/news/2026/3/12/eight-arab-islamic-countries-condemn-israeli-closure-of-al-aqsa-mosque?traffic_source=rss",
      "pubDate": "Thu, 12 Mar 2026 00:04:37 +0000",
      "source": "aljazeera",
      "snippet": "For the past 12 days, Israel has closed Al-Aqsa Mosque and restricted movement in the Old City of Jerusalem.",
      "isNew": true,
      "_sourceCount": 1,
      "_isDuplicated": false,
      "_clusterSize": 1,
      "_isDuplicate": false
    }
  ],
  "news_digest": {
    "categories": [
      {
        "category_id": "military",
        "category_name": "군사 작전",
        "category_icon": "⚔️",
        "count": 24,
        "new_count": 24,
        "articles": [
          {
            "title": "Middle East crisis live: Iraqi tankers hit as Iran targets oil supplies; US orders petroleum reserve release in bid to calm markets",
            "link": "https://www.theguardian.com/world/live/2026/mar/11/iran-war-live-updates-trump-oil-hormuz-protestors-us-israel-beirut-middle-east-latest-news",
            "source": "guardian",
            "sources": [
              "guardian"
            ],
            "pubDate": "Thu, 12 Mar 2026 04:04:57 GMT",
            "snippet": "Iraq officials say at least one person was killed in the attack on the tankers; US to release 172m barrels of oil from strategic reserveIran escalates attacks on infrastructure and transport across th",
            "isNew": true
          },
          {
            "title": "Fuel tank fire rages in Bahrain after Iranian attack",
            "link": "https://www.aljazeera.com/video/newsfeed/2026/3/12/fuel-tank-fire-rages-in-bahrain-after-iranian-attack?traffic_source=rss",
            "source": "aljazeera",
            "sources": [
              "aljazeera"
            ],
            "pubDate": "Thu, 12 Mar 2026 03:15:15 +0000",
            "snippet": "Bahrain&#039;s interior ministry released footage of a massive blaze at a fuel storage facility following an Iranian attack.",
            "isNew": true
          },
          {
            "title": "Countries Scramble to Shore Up Global Oil Supplies as Ships Are Attacked",
            "link": "https://www.nytimes.com/2026/03/11/world/middleeast/oil-ships-lebanon-iran-israel.html",
            "source": "nytimes",
            "sources": [
              "nytimes"
            ],
            "pubDate": "Thu, 12 Mar 2026 02:52:17 +0000",
            "snippet": "The United States and Israel launched more strikes against Iran, where crowds mourned military commanders killed in the war. Israel also bombed targets in Lebanon, where the death toll climbed.",
            "isNew": true
          },
          {
            "title": "Who bombed the Iranian girls’ school, killing more than 170? What we know",
            "link": "https://www.aljazeera.com/news/2026/3/12/who-bombed-the-iranian-girls-school-killing-more-than-170-what-we-know?traffic_source=rss",
            "source": "aljazeera",
            "sources": [
              "aljazeera"
            ],
            "pubDate": "Thu, 12 Mar 2026 02:21:15 +0000",
            "snippet": "The attack on Shajareh Tayyebeh Elementary School quickly became a focal point of concern over civilian casualties.",
            "isNew": true
          },
          {
            "title": "US responsible for deadly missile strike on Iran school, preliminary inquiry says",
            "link": "https://www.theguardian.com/world/2026/mar/11/iran-war-missile-strike-elementary-school",
            "source": "guardian",
            "sources": [
              "guardian",
              "nytimes"
            ],
            "pubDate": "Wed, 11 Mar 2026 18:23:49 GMT",
            "snippet": "Strike that killed at least 175 people, most of them children, reportedly due to targeting mistake by US military plannersMinab school bombing: a visual guideSign up for the Breaking News US newslette",
            "isNew": true
          },
          {
            "title": "Israel Bombards Lebanese Capital in Latest Round of Strikes",
            "link": "https://www.nytimes.com/2026/03/11/world/middleeast/beirut-lebanon-israel-strikes.html",
            "source": "nytimes",
            "sources": [
              "nytimes"
            ],
            "pubDate": "Thu, 12 Mar 2026 00:48:59 +0000",
            "snippet": "Lebanon’s health ministry said at least seven people were killed in the Beirut attacks early Thursday.",
            "isNew": true
          },
          {
            "title": "Israel bombards Beirut suburbs and southern Lebanon as conflict with Hezbollah escalates",
            "link": "https://www.theguardian.com/world/2026/mar/12/israel-bombards-beirut-southern-lebanon-hezbollah",
            "source": "guardian",
            "sources": [
              "guardian"
            ],
            "pubDate": "Thu, 12 Mar 2026 00:10:20 GMT",
            "snippet": "Hezbollah and Iran had launched joint attack on more than 50 targets including Israeli military basesMiddle East live – latest updatesIsraeli warplanes bombarded Beirut’s southern suburbs and southern",
            "isNew": true
          },
          {
            "title": "Iran war live: Oil tankers hit in Iraq, Tehran sets 3 conditions for peace",
            "link": "https://www.aljazeera.com/news/liveblog/2026/3/12/iran-war-live-oil-tankers-hit-in-iraq-tehran-sets-3-conditions-for-peace?traffic_source=rss",
            "source": "aljazeera",
            "sources": [
              "aljazeera"
            ],
            "pubDate": "Thu, 12 Mar 2026 00:00:00 +0000",
            "snippet": "Iran demands recognition of its rights, war reparations and guarantees against future aggression to end the war. \n",
            "isNew": true
          },
          {
            "title": "‘Proud as a Qatari’: Country’s PM salutes resilience amid Iranian attacks",
            "link": "https://www.aljazeera.com/news/2026/3/11/proud-as-a-qatari-countrys-pm-salutes-resilience-amid-iranian-attacks?traffic_source=rss",
            "source": "aljazeera",
            "sources": [
              "aljazeera"
            ],
            "pubDate": "Wed, 11 Mar 2026 23:56:57 +0000",
            "snippet": "The country&#039;s prime minister urges resilience, says government committed to ensuring people&#039;s lives are not disrupted. ",
            "isNew": true
          },
          {
            "title": "Massive fires on two oil tankers after attack in Iraqi waters",
            "link": "https://www.aljazeera.com/video/newsfeed/2026/3/11/massive-fires-on-two-oil-tankers-after-attack-in-iraqi-waters?traffic_source=rss",
            "source": "aljazeera",
            "sources": [
              "aljazeera"
            ],
            "pubDate": "Wed, 11 Mar 2026 23:19:04 +0000",
            "snippet": "Two foreign tankers were seen ablaze in Iraqi territorial waters after a strike near the al-Faw port.",
            "isNew": true
          }
        ]
      },
      {
        "category_id": "politics",
        "category_name": "국내 정치",
        "category_icon": "🏛️",
        "count": 6,
        "new_count": 6,
        "articles": [
          {
            "title": "Iran’s authorities warn against protests as Israel threatens Basij forces",
            "link": "https://www.aljazeera.com/news/2026/3/12/irans-authorities-warn-against-protests-as-israel-threatens-basij-forces?traffic_source=rss",
            "source": "aljazeera",
            "sources": [
              "aljazeera"
            ],
            "pubDate": "Thu, 12 Mar 2026 01:35:06 +0000",
            "snippet": "Police chief says protesters seen as acting at the behest of the US and Israel will be treated as enemies. ",
            "isNew": true
          },
          {
            "title": "Strong or Weak? How Trump Picks His Battles.",
            "link": "https://www.nytimes.com/2026/03/11/us/politics/trump-adversaries-picking-battles.html",
            "source": "nytimes",
            "sources": [
              "nytimes"
            ],
            "pubDate": "Wed, 11 Mar 2026 22:24:52 +0000",
            "snippet": "Despite his tough talk, President Trump has consistently made allowances for countries he sees as powerful or dominant.",
            "isNew": true
          },
          {
            "title": "Ecuador prepares for attack on ‘criminal economy’ with Trump backing",
            "link": "https://www.aljazeera.com/news/2026/3/11/ecuador-prepares-for-attack-on-criminal-economy-with-trump-backing?traffic_source=rss",
            "source": "aljazeera",
            "sources": [
              "aljazeera"
            ],
            "pubDate": "Wed, 11 Mar 2026 21:10:20 +0000",
            "snippet": "Interior Minister John Reimberg warned for residents in four provinces to obey a curfew to avoid &#039;collateral damage&#039;.",
            "isNew": true
          },
          {
            "title": "Iran’s New Supreme Leader Was Wounded Early in the War, Iranian and Israeli Officials Say",
            "link": "https://www.nytimes.com/2026/03/11/world/middleeast/khamenei-iran-leader-injured.html",
            "source": "nytimes",
            "sources": [
              "nytimes"
            ],
            "pubDate": "Wed, 11 Mar 2026 20:52:30 +0000",
            "snippet": "Officials say Mojtaba Khamenei’s legs were hurt, but the circumstances as well as the extent of his injuries were unclear. He has remained out of view since being announced as leader three days ago.",
            "isNew": true
          },
          {
            "title": "Elevating injured Mojtaba Khamenei to supreme leader shows Iranian war machine can run on autopilot",
            "link": "https://www.theguardian.com/world/2026/mar/11/elevating-injured-mojtaba-khamenei-supreme-leader-shows-iranian-military-machine-autopilot",
            "source": "guardian",
            "sources": [
              "guardian"
            ],
            "pubDate": "Wed, 11 Mar 2026 18:31:52 GMT",
            "snippet": "Lack of public appearances prompted speculation about new leader’s mortality after multiple family members diedThe confirmation that Iran’s new supreme leader, Mojtaba Khamenei, was injured in the fir",
            "isNew": true
          },
          {
            "title": "Ben Jennings on Trump and Hegseth: mission accomplished? – cartoon",
            "link": "https://www.theguardian.com/commentisfree/picture/2026/mar/11/ben-jennings-donald-trump-pete-hegseth-cartoon",
            "source": "guardian",
            "sources": [
              "guardian"
            ],
            "pubDate": "Wed, 11 Mar 2026 18:17:13 GMT",
            "snippet": " Continue reading...",
            "isNew": true
          }
        ]
      },
      {
        "category_id": "economy",
        "category_name": "경제 영향",
        "category_icon": "📊",
        "count": 5,
        "new_count": 5,
        "articles": [
          {
            "title": "U.S. to Release 172 Million Barrels of Oil From Strategic Reserves, Energy Dept. Says",
            "link": "https://www.nytimes.com/2026/03/11/world/middleeast/us-oil-reserves-trump-iran.html",
            "source": "nytimes",
            "sources": [
              "nytimes"
            ],
            "pubDate": "Thu, 12 Mar 2026 02:06:39 +0000",
            "snippet": "The move aims to prevent prices from rising further because of the war in the Middle East.",
            "isNew": true
          },
          {
            "title": "Ships hit in Strait of Hormuz as countries agree to release emergency oil reserves",
            "link": "https://www.bbc.com/news/articles/cr5l988qr47o?at_medium=RSS&at_campaign=rss",
            "source": "bbc",
            "sources": [
              "bbc"
            ],
            "pubDate": "Wed, 11 Mar 2026 23:07:46 GMT",
            "snippet": "Pressure has intensified on the strait, one of the world's most important shipping lanes, since Israel and the US attacked Iran late last month. ",
            "isNew": true
          },
          {
            "title": "What Happened in the U.S.-Israeli War on Iran on Wednesday",
            "link": "https://www.nytimes.com/2026/03/11/world/middleeast/iran-war-middle-east-recap.html",
            "source": "nytimes",
            "sources": [
              "nytimes"
            ],
            "pubDate": "Wed, 11 Mar 2026 22:56:45 +0000",
            "snippet": "Israel and the Iran-backed armed group Hezbollah in Lebanon traded strikes on Wednesday. Three ships were hit near the Strait of Hormuz, a vital oil route.",
            "isNew": true
          },
          {
            "title": "Why does Iran war pose more dilemmas for Europe?",
            "link": "https://www.aljazeera.com/video/inside-story/2026/3/11/why-does-the-iran-war-pose-more-dilemmas-for-europe?traffic_source=rss",
            "source": "aljazeera",
            "sources": [
              "aljazeera"
            ],
            "pubDate": "Wed, 11 Mar 2026 20:41:48 +0000",
            "snippet": "Europe faces stiff competition with Asia for energy supplies as Russia profits.",
            "isNew": true
          },
          {
            "title": "Three merchant ships struck as tensions rise in Hormuz strait amid Iran war",
            "link": "https://www.theguardian.com/news/2026/mar/11/us-iran-strait-of-hormuz-mine-boat-attacks",
            "source": "guardian",
            "sources": [
              "guardian"
            ],
            "pubDate": "Wed, 11 Mar 2026 18:15:49 GMT",
            "snippet": "Crew of Thai-registered bulk carrier forced to flee fire, as US says it has destroyed 16 Iranian mine-laying vesselsMiddle East crisis live – latest updatesThree merchant ships have been struck in and",
            "isNew": true
          }
        ]
      },
      {
        "category_id": "diplomacy",
        "category_name": "외교/협상",
        "category_icon": "🤝",
        "count": 4,
        "new_count": 4,
        "articles": [
          {
            "title": "U.N. Security Council Condemns Iran’s Retaliatory Strikes in the Middle East",
            "link": "https://www.nytimes.com/2026/03/11/world/middleeast/un-security-council-condemns-iran-strikes.html",
            "source": "nytimes",
            "sources": [
              "nytimes",
              "aljazeera"
            ],
            "pubDate": "Thu, 12 Mar 2026 01:32:08 +0000",
            "snippet": "In an overwhelming vote, the council backed a resolution condemning Iran. A Russian proposal calling for an end to the war that didn’t assign blame or even name the parties, was rejected.",
            "isNew": true
          },
          {
            "title": "New files show British PM warned of ‘reputational risks’ with Mandelson",
            "link": "https://www.aljazeera.com/news/2026/3/11/new-files-show-british-pm-warned-of-reputational-risks-with-mandelson?traffic_source=rss",
            "source": "aljazeera",
            "sources": [
              "aljazeera"
            ],
            "pubDate": "Wed, 11 Mar 2026 23:14:25 +0000",
            "snippet": "More than 100 pages of documents were published which covered the process of Peter Mandelson’s appointment as US envoy.",
            "isNew": true
          },
          {
            "title": "South Africa summons new US ambassador over ‘undiplomatic remarks’",
            "link": "https://www.aljazeera.com/news/2026/3/11/south-africa-summons-new-us-ambassador-over-undiplomatic-remarks?traffic_source=rss",
            "source": "aljazeera",
            "sources": [
              "aljazeera"
            ],
            "pubDate": "Wed, 11 Mar 2026 22:33:32 +0000",
            "snippet": "US President Trump has claimed South Africa is engaged in a campaign of white persecution, which Pretoria denies. ",
            "isNew": true
          },
          {
            "title": "UN Security Council adopts Gulf countries’ draft resolution",
            "link": "https://www.aljazeera.com/video/newsfeed/2026/3/11/un-security-council-adopts-gulf-countries-draft-resolution-2?traffic_source=rss",
            "source": "aljazeera",
            "sources": [
              "aljazeera"
            ],
            "pubDate": "Wed, 11 Mar 2026 21:11:05 +0000",
            "snippet": "The UN Security Council has passed a resolution put forward by GCC members calling on Iran to halt attacks on the Gulf. ",
            "isNew": true
          }
        ]
      },
      {
        "category_id": "humanitarian",
        "category_name": "인도주의/피해",
        "category_icon": "🏥",
        "count": 4,
        "new_count": 4,
        "articles": [
          {
            "title": "Fire erupts at Gaza camp after Israeli attack hits tents",
            "link": "https://www.aljazeera.com/video/newsfeed/2026/3/12/fire-erupts-at-gaza-camp-after-israeli-attack-hits-tents?traffic_source=rss",
            "source": "aljazeera",
            "sources": [
              "aljazeera"
            ],
            "pubDate": "Thu, 12 Mar 2026 03:25:41 +0000",
            "snippet": "Fire broke out at tents sheltering displaced Palestinians in Gaza’s Al-Ansar refugee camp after an Israeli strike.",
            "isNew": true
          },
          {
            "title": "Israeli strike hits Beirut waterfront near tents of displaced",
            "link": "https://www.aljazeera.com/video/newsfeed/2026/3/12/israeli-strike-hits-beirut-waterfront-near-tents-of-displaced?traffic_source=rss",
            "source": "aljazeera",
            "sources": [
              "aljazeera"
            ],
            "pubDate": "Thu, 12 Mar 2026 01:53:23 +0000",
            "snippet": "At least six people are dead from an Israeli strike on Beirut’s Ramlet al-Baida seafront.",
            "isNew": true
          },
          {
            "title": "Iran escalates attacks on infrastructure and transport networks across the Gulf",
            "link": "https://www.theguardian.com/world/2026/mar/11/iran-escalates-attacks-on-infrastructure-and-transport-networks-across-the-gulf",
            "source": "guardian",
            "sources": [
              "guardian"
            ],
            "pubDate": "Wed, 11 Mar 2026 23:02:36 GMT",
            "snippet": "Iranian officials warn of ‘war of attrition’ and global economic chaos as energy supplies are throttledMiddle East crisis – live updatesIran dramatically escalated its strategy of striking civilian in",
            "isNew": true
          },
          {
            "title": "Displaced Lebanese families seek refuge in school shelter",
            "link": "https://www.aljazeera.com/video/newsfeed/2026/3/11/displaced-lebanese-families-seek-refuge-in-school-shelter?traffic_source=rss",
            "source": "aljazeera",
            "sources": [
              "aljazeera"
            ],
            "pubDate": "Wed, 11 Mar 2026 20:54:36 +0000",
            "snippet": "Displaced families from southern Lebanon have taken refuge in a school in Sidon after fleeing Israeli attacks.",
            "isNew": true
          }
        ]
      },
      {
        "category_id": "other",
        "category_name": "기타",
        "category_icon": "📰",
        "count": 3,
        "new_count": 3,
        "articles": [
          {
            "title": "Eight Arab, Islamic countries condemn Israeli closure of Al-Aqsa Mosque",
            "link": "https://www.aljazeera.com/news/2026/3/12/eight-arab-islamic-countries-condemn-israeli-closure-of-al-aqsa-mosque?traffic_source=rss",
            "source": "aljazeera",
            "sources": [
              "aljazeera"
            ],
            "pubDate": "Thu, 12 Mar 2026 00:04:37 +0000",
            "snippet": "For the past 12 days, Israel has closed Al-Aqsa Mosque and restricted movement in the Old City of Jerusalem.",
            "isNew": true
          },
          {
            "title": "Here we are again: inside the 13 March Guardian Weekly",
            "link": "https://www.theguardian.com/news/2026/mar/11/here-we-are-again-inside-the-13-march-guardian-weekly",
            "source": "guardian",
            "sources": [
              "guardian"
            ],
            "pubDate": "Wed, 11 Mar 2026 18:00:55 GMT",
            "snippet": "Why hasn’t the US learned the lessons of two Gulf wars? Plus Iran’s supreme statement of defianceGet the Guardian Weekly delivered to your home addressWhen news breaks that dominates the agenda to the",
            "isNew": true
          },
          {
            "title": "Iran Soccer Players Seeking Asylum Are Part of a History of Athlete Defections",
            "link": "https://www.nytimes.com/2026/03/11/sports/iran-women-soccer-defect.html",
            "source": "nytimes",
            "sources": [
              "nytimes"
            ],
            "pubDate": "Wed, 11 Mar 2026 17:49:53 +0000",
            "snippet": "Members of the Iranian soccer team who chose to remain in Australia this week are far from the first to travel to a competition and stay there.",
            "isNew": true
          }
        ]
      },
      {
        "category_id": "regional",
        "category_name": "지역 정세",
        "category_icon": "🌍",
        "count": 2,
        "new_count": 2,
        "articles": [
          {
            "title": "Qatar PM urges resilience and unity amid Iran strikes",
            "link": "https://www.aljazeera.com/video/newsfeed/2026/3/12/qatar-pm-urges-resilience-and-unity-amid-iran-strikes?traffic_source=rss",
            "source": "aljazeera",
            "sources": [
              "aljazeera"
            ],
            "pubDate": "Thu, 12 Mar 2026 00:35:43 +0000",
            "snippet": "Qatar’s Prime Minister calls for strengthening the country’s ability to withstand “hardship” amid regional war.",
            "isNew": true
          },
          {
            "title": "Israel sends an extra infantry brigade to Lebanon’s border.",
            "link": "https://www.nytimes.com/live/2026/03/11/world/iran-war-news-trump-oil-israel/israel-sends-an-extra-infantry-battalion-to-lebanons-border",
            "source": "nytimes",
            "sources": [
              "nytimes"
            ],
            "pubDate": "Wed, 11 Mar 2026 18:35:01 +0000",
            "snippet": "",
            "isNew": true
          }
        ]
      }
    ],
    "recent_30min": {
      "total_new": 50,
      "by_category": {
        "military": {
          "count": 25,
          "titles": [
            {
              "title": "Middle East crisis live: Iraqi tankers hit as Iran targets oil supplies; US orders petroleum reserve release in bid to calm markets",
              "link": "https://www.theguardian.com/world/live/2026/mar/11/iran-war-live-updates-trump-oil-hormuz-protestors-us-israel-beirut-middle-east-latest-news",
              "source": "guardian"
            },
            {
              "title": "Fuel tank fire rages in Bahrain after Iranian attack",
              "link": "https://www.aljazeera.com/video/newsfeed/2026/3/12/fuel-tank-fire-rages-in-bahrain-after-iranian-attack?traffic_source=rss",
              "source": "aljazeera"
            },
            {
              "title": "Countries Scramble to Shore Up Global Oil Supplies as Ships Are Attacked",
              "link": "https://www.nytimes.com/2026/03/11/world/middleeast/oil-ships-lebanon-iran-israel.html",
              "source": "nytimes"
            },
            {
              "title": "Who bombed the Iranian girls’ school, killing more than 170? What we know",
              "link": "https://www.aljazeera.com/news/2026/3/12/who-bombed-the-iranian-girls-school-killing-more-than-170-what-we-know?traffic_source=rss",
              "source": "aljazeera"
            },
            {
              "title": "U.S. at Fault in Strike on School in Iran, Preliminary Inquiry Says",
              "link": "https://www.nytimes.com/2026/03/11/us/politics/iran-school-missile-strike.html",
              "source": "nytimes"
            }
          ]
        },
        "humanitarian": {
          "count": 4,
          "titles": [
            {
              "title": "Fire erupts at Gaza camp after Israeli attack hits tents",
              "link": "https://www.aljazeera.com/video/newsfeed/2026/3/12/fire-erupts-at-gaza-camp-after-israeli-attack-hits-tents?traffic_source=rss",
              "source": "aljazeera"
            },
            {
              "title": "Israeli strike hits Beirut waterfront near tents of displaced",
              "link": "https://www.aljazeera.com/video/newsfeed/2026/3/12/israeli-strike-hits-beirut-waterfront-near-tents-of-displaced?traffic_source=rss",
              "source": "aljazeera"
            },
            {
              "title": "Iran escalates attacks on infrastructure and transport networks across the Gulf",
              "link": "https://www.theguardian.com/world/2026/mar/11/iran-escalates-attacks-on-infrastructure-and-transport-networks-across-the-gulf",
              "source": "guardian"
            },
            {
              "title": "Displaced Lebanese families seek refuge in school shelter",
              "link": "https://www.aljazeera.com/video/newsfeed/2026/3/11/displaced-lebanese-families-seek-refuge-in-school-shelter?traffic_source=rss",
              "source": "aljazeera"
            }
          ]
        },
        "diplomacy": {
          "count": 5,
          "titles": [
            {
              "title": "UN Security Council adopts resolution condemning Iran’s attacks in the Gulf",
              "link": "https://www.aljazeera.com/news/2026/3/12/un-security-council-adopts-resolution-condemning-irans-attacks-in-the-gulf?traffic_source=rss",
              "source": "aljazeera"
            },
            {
              "title": "U.N. Security Council Condemns Iran’s Retaliatory Strikes in the Middle East",
              "link": "https://www.nytimes.com/2026/03/11/world/middleeast/un-security-council-condemns-iran-strikes.html",
              "source": "nytimes"
            },
            {
              "title": "New files show British PM warned of ‘reputational risks’ with Mandelson",
              "link": "https://www.aljazeera.com/news/2026/3/11/new-files-show-british-pm-warned-of-reputational-risks-with-mandelson?traffic_source=rss",
              "source": "aljazeera"
            },
            {
              "title": "South Africa summons new US ambassador over ‘undiplomatic remarks’",
              "link": "https://www.aljazeera.com/news/2026/3/11/south-africa-summons-new-us-ambassador-over-undiplomatic-remarks?traffic_source=rss",
              "source": "aljazeera"
            },
            {
              "title": "UN Security Council adopts Gulf countries’ draft resolution",
              "link": "https://www.aljazeera.com/video/newsfeed/2026/3/11/un-security-council-adopts-gulf-countries-draft-resolution-2?traffic_source=rss",
              "source": "aljazeera"
            }
          ]
        },
        "economy": {
          "count": 5,
          "titles": [
            {
              "title": "U.S. to Release 172 Million Barrels of Oil From Strategic Reserves, Energy Dept. Says",
              "link": "https://www.nytimes.com/2026/03/11/world/middleeast/us-oil-reserves-trump-iran.html",
              "source": "nytimes"
            },
            {
              "title": "Ships hit in Strait of Hormuz as countries agree to release emergency oil reserves",
              "link": "https://www.bbc.com/news/articles/cr5l988qr47o?at_medium=RSS&at_campaign=rss",
              "source": "bbc"
            },
            {
              "title": "What Happened in the U.S.-Israeli War on Iran on Wednesday",
              "link": "https://www.nytimes.com/2026/03/11/world/middleeast/iran-war-middle-east-recap.html",
              "source": "nytimes"
            },
            {
              "title": "Why does Iran war pose more dilemmas for Europe?",
              "link": "https://www.aljazeera.com/video/inside-story/2026/3/11/why-does-the-iran-war-pose-more-dilemmas-for-europe?traffic_source=rss",
              "source": "aljazeera"
            },
            {
              "title": "Three merchant ships struck as tensions rise in Hormuz strait amid Iran war",
              "link": "https://www.theguardian.com/news/2026/mar/11/us-iran-strait-of-hormuz-mine-boat-attacks",
              "source": "guardian"
            }
          ]
        },
        "politics": {
          "count": 6,
          "titles": [
            {
              "title": "Iran’s authorities warn against protests as Israel threatens Basij forces",
              "link": "https://www.aljazeera.com/news/2026/3/12/irans-authorities-warn-against-protests-as-israel-threatens-basij-forces?traffic_source=rss",
              "source": "aljazeera"
            },
            {
              "title": "Strong or Weak? How Trump Picks His Battles.",
              "link": "https://www.nytimes.com/2026/03/11/us/politics/trump-adversaries-picking-battles.html",
              "source": "nytimes"
            },
            {
              "title": "Ecuador prepares for attack on ‘criminal economy’ with Trump backing",
              "link": "https://www.aljazeera.com/news/2026/3/11/ecuador-prepares-for-attack-on-criminal-economy-with-trump-backing?traffic_source=rss",
              "source": "aljazeera"
            },
            {
              "title": "Iran’s New Supreme Leader Was Wounded Early in the War, Iranian and Israeli Officials Say",
              "link": "https://www.nytimes.com/2026/03/11/world/middleeast/khamenei-iran-leader-injured.html",
              "source": "nytimes"
            },
            {
              "title": "Elevating injured Mojtaba Khamenei to supreme leader shows Iranian war machine can run on autopilot",
              "link": "https://www.theguardian.com/world/2026/mar/11/elevating-injured-mojtaba-khamenei-supreme-leader-shows-iranian-military-machine-autopilot",
              "source": "guardian"
            }
          ]
        },
        "regional": {
          "count": 2,
          "titles": [
            {
              "title": "Qatar PM urges resilience and unity amid Iran strikes",
              "link": "https://www.aljazeera.com/video/newsfeed/2026/3/12/qatar-pm-urges-resilience-and-unity-amid-iran-strikes?traffic_source=rss",
              "source": "aljazeera"
            },
            {
              "title": "Israel sends an extra infantry brigade to Lebanon’s border.",
              "link": "https://www.nytimes.com/live/2026/03/11/world/iran-war-news-trump-oil-israel/israel-sends-an-extra-infantry-battalion-to-lebanons-border",
              "source": "nytimes"
            }
          ]
        },
        "other": {
          "count": 3,
          "titles": [
            {
              "title": "Eight Arab, Islamic countries condemn Israeli closure of Al-Aqsa Mosque",
              "link": "https://www.aljazeera.com/news/2026/3/12/eight-arab-islamic-countries-condemn-israeli-closure-of-al-aqsa-mosque?traffic_source=rss",
              "source": "aljazeera"
            },
            {
              "title": "Here we are again: inside the 13 March Guardian Weekly",
              "link": "https://www.theguardian.com/news/2026/mar/11/here-we-are-again-inside-the-13-march-guardian-weekly",
              "source": "guardian"
            },
            {
              "title": "Iran Soccer Players Seeking Asylum Are Part of a History of Athlete Defections",
              "link": "https://www.nytimes.com/2026/03/11/sports/iran-women-soccer-defect.html",
              "source": "nytimes"
            }
          ]
        }
      }
    }
  },
  "historical_comparison": [
    {
      "name": "걸프전 (1991)",
      "duration_days": 42,
      "type": "공습→지상전",
      "involved_countries": 35,
      "ended_by": "군사적 패배"
    },
    {
      "name": "이라크전 주요전투 (2003)",
      "duration_days": 42,
      "type": "침공",
      "involved_countries": 4,
      "ended_by": "정권 교체"
    },
    {
      "name": "2006 레바논 전쟁",
      "duration_days": 34,
      "type": "공습+지상전",
      "involved_countries": 2,
      "ended_by": "UN 휴전"
    },
    {
      "name": "2008 가자 전쟁",
      "duration_days": 22,
      "type": "공습→지상전",
      "involved_countries": 2,
      "ended_by": "일방적 휴전"
    },
    {
      "name": "2014 가자 전쟁",
      "duration_days": 50,
      "type": "공습+지상전",
      "involved_countries": 2,
      "ended_by": "협상 휴전"
    },
    {
      "name": "리비아 NATO 개입 (2011)",
      "duration_days": 222,
      "type": "공습 작전",
      "involved_countries": 18,
      "ended_by": "정권 교체"
    },
    {
      "name": "포클랜드 전쟁 (1982)",
      "duration_days": 74,
      "type": "해·공·지상전",
      "involved_countries": 2,
      "ended_by": "군사적 패배"
    },
    {
      "name": "코소보 NATO 폭격 (1999)",
      "duration_days": 78,
      "type": "공습 작전",
      "involved_countries": 19,
      "ended_by": "항복"
    },
    {
      "name": "이스라엘-하마스 (2023-25)",
      "duration_days": 470,
      "type": "공습+지상전",
      "involved_countries": 2,
      "ended_by": "협상 휴전"
    },
    {
      "name": "이란-이라크 전쟁 (1980-88)",
      "duration_days": 2922,
      "type": "총력전",
      "involved_countries": 2,
      "ended_by": "UN 휴전"
    },
    {
      "name": "러시아-우크라이나 전쟁 (2022-)",
      "duration_days": 1105,
      "type": "전면 침공+소모전",
      "involved_countries": 2,
      "ended_by": "진행 중"
    },
    {
      "name": "2025 이란-이스라엘 교전",
      "duration_days": 12,
      "type": "공습 작전",
      "involved_countries": 3,
      "ended_by": "중재 휴전"
    }
  ],
  "economic_indicators": {
    "US10Y": {
      "price": 4.21,
      "change": 0.07,
      "changePercent": 1.69,
      "prev": 4.14
    },
    "VIX": {
      "price": 24.23,
      "change": -0.7,
      "changePercent": -2.81,
      "prev": 24.93
    },
    "WTI": {
      "price": 94.45,
      "change": 7.2,
      "changePercent": 8.25,
      "prev": 87.25
    },
    "GOLD": {
      "price": 5155.6,
      "change": -11.8,
      "changePercent": -0.23,
      "prev": 5167.4
    },
    "US2Y": {
      "price": 3.6,
      "change": 0,
      "changePercent": 0,
      "prev": 3.6
    },
    "BRENT": {
      "price": 95.9,
      "change": 3.92,
      "changePercent": 4.26,
      "prev": 91.98
    },
    "DXY": {
      "price": 99.47,
      "change": 0.24,
      "changePercent": 0.24,
      "prev": 99.23
    }
  },
  "critical_events": [
    {
      "id": "unilateral_deescalation",
      "name": "일방적 전투 축소/자제 선언",
      "severity": "high",
      "confidence": 0.6666666666666666,
      "matchCount": 2,
      "direction": "shorten"
    },
    {
      "id": "capital_attack",
      "name": "수도 직접 공격/포위",
      "severity": "high",
      "confidence": 1,
      "matchCount": 4,
      "direction": "shorten"
    },
    {
      "id": "conflict_expansion",
      "name": "전선 확대/신규 참전국",
      "severity": "moderate",
      "confidence": 0.6666666666666666,
      "matchCount": 2,
      "direction": "lengthen"
    }
  ],
  "feeds_loaded": 7,
  "feeds_total": 8
}